Workbook

Sheet Contents (Índice)
D20: Nu Holdings Ltd.
D21: Investor Relations
D22: investors@nubank.com.br
B24: MANAGERIAL INFORMATION | F24: CONSOLIDATED FINANCIAL STATEMENTS IN IFRS
B26: Managerial P&L | F26: Consolidated Statement of Income
B27: Managerial Indicators | F27: Consolidated Balance Sheet
B28: Operating Figures | F28: Consolidated Statement of Cash Flow
B29: Non-Performing Loans (NPLs) | F29: Revenue Breakdown
F30: Expenses Breakdown
F31: Credit Operations

Sheet Managerial P&L 
B2: Nu Holdings Ltd.
B3: Managerial Indicators
B4: Amounts in million of US$, unless otherwise noted
B5: Back to Contents
C8: 3-MONTH PERIOD ENDED
C9: 44286 | D9: 44377 | E9: 44469 | F9: 44561 | G9: 44651 | H9: 44742 | I9: 44834 | J9: 44926 | K9: 45016 | L9: 45107 | M9: 45199 | N9: 31/12/2023 | O9: 31/03/2024 | P9: 30/06/2024 | Q9: 30/09/2024 | R9: 31/12/2024 | S9: 31/03/2025 | T9: 30/06/2025 | U9: 30/09/2025 | V9: 31/12/2025
C10: US$ | D10: US$ | E10: US$ | F10: US$ | G10: US$ | H10: US$ | I10: US$ | J10: US$ | K10: US$ | L10: US$ | M10: US$ | N10: US$ | O10: US$ | P10: US$ | Q10: US$ | R10: US$ | S10: US$ | T10: US$ | U10: US$ | V10: US$
B11: Total Revenue | C11: 247.185 | D11: 338.62 | E11: 483.044 | F11: 591.206 | G11: 879.075 | H11: 1163.24 | I11: 1316.162 | J11: 1463.394 | K11: 1632.23 | L11: 1892.365 | M11: 2171.312 | N11: 2455.115 | O11: 2722.923 | P11: 2877.952 | Q11: 2969.534 | R11: 3100.702 | S11: 3372.725 | T11: 3772.305 | U11: 4317.219 | V11: 4857.306
B12: Credit Income | C12: 90.962 | D12: 130.2 | E12: 178.633 | F12: 203.839 | G12: 383.667 | H12: 471.951 | I12: 512.65 | J12: 578.803 | K12: 734.639 | L12: 946.937 | M12: 1144.058 | N12: 1388.524 | O12: 1608.779 | P12: 1736.527 | Q12: 1740.306 | R12: 1783.591 | S12: 1976.011 | T12: 2239.789 | U12: 2489.195 | V12: 2777.963
B13: Float Income | C13: 36.477 | D13: 54.859 | E13: 116.687 | F13: 189.163 | G13: 235.85 | H13: 384.502 | I13: 482.546 | J13: 527.111 | K13: 531.88 | L13: 572.919 | M13: 617.077 | N13: 609.956 | O13: 655.605 | P13: 690.009 | Q13: 761.229 | R13: 806.365 | S13: 880.142 | T13: 990.931 | U13: 1225.272 | V13: 1408.906
B14: Fee Revenue | C14: 119.746 | D14: 153.561 | E14: 187.724 | F14: 198.204 | G14: 259.558 | H14: 306.787 | I14: 320.966 | J14: 357.48 | K14: 365.712 | L14: 372.509 | M14: 410.177 | N14: 456.634 | O14: 458.539 | P14: 451.416 | Q14: 467.999 | R14: 510.746 | S14: 516.572 | T14: 541.585 | U14: 602.752 | V14: 670.437
B16: Total Direct Costs | C16: -132.93 | D16: -173.508 | E16: -260.977 | F16: -414.396 | G16: -590.192 | H16: -843.409 | I16: -912.31 | J16: -913.332 | K16: -1013.067 | L16: -1143.331 | M16: -1302.73 | N16: -1371.509 | O16: -1609.409 | P16: -1584.712 | Q16: -1667.82 | R16: -1783.674 | S16: -2045.202 | T16: -2252.982 | U16: -2506.032 | V16: -2896.24
B17: Funding Cost | C17: -29.067 | D17: -53.886 | E17: -95.458 | F17: -159.158 | G17: -256.243 | H17: -376.357 | I17: -451.034 | J17: -395.735 | K17: -429.426 | L17: -438.676 | M17: -510.492 | N17: -530.431 | O17: -599.603 | P17: -648.426 | Q17: -713.321 | R17: -761.83 | S17: -841.09 | T17: -1007.269 | U17: -1237.186 | V17: -1349.973
B18: Cost of Credit | C18: -73.97 | D18: -86.018 | E18: -132.94 | F18: -217.49 | G18: -292.482 | H18: -369.635 | I18: -384.329 | J18: -426.999 | K18: -485.581 | L18: -605.184 | M18: -664.483 | N18: -700.867 | O18: -863.359 | P18: -783.74 | Q18: -801.918 | R18: -849.905 | S18: -1041.848 | T18: -1051.053 | U18: -1035.802 | V18: -1313.223
B19: Transaction Cost | C19: -28.377 | D19: -32.148 | E19: -30.335 | F19: -34.217 | G19: -36.182 | H19: -50.275 | I19: -45.822 | J19: -51.921 | K19: -55.277 | L19: -46.891 | M19: -63.97 | N19: -64.51 | O19: -63.551 | P19: -64.511 | Q19: -64.427 | R19: -79.921 | S19: -63.082 | T19: -83.232 | U19: -108.227 | V19: -99.019
B20: Revenue-Based Taxes | C20: -1.516 | D20: -1.456 | E20: -2.244 | F20: -3.531 | G20: -5.285 | H20: -47.142 | I20: -31.125 | J20: -38.676 | K20: -42.783 | L20: -52.58 | M20: -63.786 | N20: -75.702 | O20: -82.896 | P20: -88.035 | Q20: -88.154 | R20: -92.019 | S20: -99.182 | T20: -111.428 | U20: -124.818 | V20: -134.025
B22: Gross Profit | C22: 114.255 | D22: 165.112 | E22: 222.067 | F22: 176.81 | G22: 288.883 | H22: 319.831 | I22: 403.852 | J22: 550.063 | K22: 619.164 | L22: 749.034 | M22: 868.583 | N22: 1083.605 | O22: 1113.514 | P22: 1293.241 | Q22: 1301.714 | R22: 1317.028 | S22: 1327.524 | T22: 1519.323 | U22: 1811.187 | V22: 1961.065
B24: Operating Expenses | C24: -167.585 | D24: -171.575 | E24: -243.681 | F24: -307.914 | G24: -356.503 | H24: -342.734 | I24: -389.448 | J24: -756.441 | K24: -366.409 | L24: -411.591 | M24: -436.829 | N24: -488.042 | O24: -522.728 | P24: -540.185 | Q24: -520.319 | R24: -469.372 | S24: -459.203 | T24: -548.104 | U24: -577.193 | V24: -652.635
B25: Customer Support and Operations | C25: -32.13 | D25: -40.968 | E25: -51.649 | F25: -65.762 | G25: -61.571 | H25: -77.703 | I25: -90.249 | J25: -105.84 | K25: -107.815 | L25: -113.309 | M25: -127.295 | N25: -139.663 | O25: -150.612 | P25: -162.917 | Q25: -135.196 | R25: -155.918 | S25: -151.475 | T25: -161.434 | U25: -174.843 | V25: -164.008
... B36: Net Income | C36: -49.483 | D36: -15.22 | E36: -34.357 | F36: -113.172 | G36: -45.004 | H36: -29.85 | I36: 7.833 | J36: -297.613 | K36: 141.751 | L36: 224.866 | M36: 303.036 | N36: 360.877 | O36: 378.814 | P36: 487.272 | Q36: 553.386 | R36: 552.64 | S36: 557.208 | T36: 636.987 | U36: 782.678 | V36: 894.799

Sheet Managerial indicators
B2: Nu Holdings Ltd.
B3: Managerial Indicators
B4: Amounts in million of US$, unless otherwise noted
B5: Back to Contents
C9: 44286 | D9: 44377 | E9: 44469 | F9: 44561 | G9: 44651 | H9: 44742 | I9: 44834 | J9: 44926 | K9: 45016 | L9: 45107 | M9: 45199 | N9: 31/12/2023 | O9: 31/03/2024 | P9: 30/06/2024 | Q9: 30/09/2024 | R9: 31/12/2024 | S9: 31/03/2025 | T9: 30/06/2025 | U9: 30/09/2025 | V9: 31/12/2025
C10: US$ | D10: US$ | E10: US$ | F10: US$ | G10: US$ | H10: US$ | I10: US$ | J10: US$ | K10: US$ | L10: US$ | M10: US$ | N10: US$ | O10: US$ | P10: US$ | Q10: US$ | R10: US$ | S10: US$ | T10: US$ | U10: US$ | V10: US$
B11: Average Revenue per Active Customer (ARPAC) - US$ | C11: 3.2 | D11: 4.1 | E11: 4.9 | F11: 5.2 | G11: 6.7 | H11: 7.8 | I11: 8 | J11: 8.2 | K11: 8.6 | L11: 9.4 | M11: 10.2 | N11: 10.8 | O11: 11.3 | P11: 11.3 | Q11: 11.1 | R11: 11.1 | S11: 11.6 | T11: 12.5 | U11: 13.8 | V11: 15
B13: Cost to Serve per Active Customer - US$ | C13: 0.8 | D13: 0.9 | E13: 0.8 | F13: 0.9 | G13: 0.7 | H13: 0.9 | I13: 0.8 | J13: 0.9 | K13: 0.9 | L13: 0.8 | M13: 0.9 | N13: 0.9 | O13: 0.9 | P13: 0.9 | Q13: 0.7 | R13: 0.8 | S13: 0.7 | T13: 0.8 | U13: 0.9 | V13: 0.8
B15: Balances EoP
B16: Credit Card non-IEP | C16: 2668 | D16: 3659 | E16: 3855 | F16: 4513 | G16: 5736 | H16: 5866 | I16: 6119 | J16: 7136 | K16: 7641 | L16: 8524 | M16: 8484 | N16: 9980 | O16: 9862 | P16: 9098 | Q16: 9669 | R16: 9522 | S16: 10281 | T16: 11595 | U16: 12678 | V16: 14181
B17: Credit Card IEP | C17: 327 | D17: 428 | E17: 512 | F17: 646 | G17: 1067 | H17: 1298 | I17: 1681 | J17: 2131 | K17: 2814 | L17: 3512 | M17: 3832 | N17: 4508 | O17: 5232 | P17: 5217 | Q17: 5518 | R17: 5097 | S17: 5988 | T17: 6630 | U17: 7350 | V17: 7570
B18: Loans to customers | C18: 304 | D18: 592 | E18: 903 | F18: 1392 | G18: 2009 | H18: 1953 | I18: 1907 | J18: 1976 | K18: 2337 | L18: 2792 | M18: 3091 | N18: 3714 | O18: 4479 | P18: 4632 | Q18: 5692 | R18: 6116 | S18: 7848 | T18: 9056 | U18: 10362 | V18: 10915
B19: Total Interest Earning Portfolio (IEP) | C19: =C17+C18 -> 631 | D19: =D17+D18 -> 1020 | E19: =E17+E18 -> 1415 | F19: =F17+F18 -> 2038 | G19: =G17+G18 -> 3076 | H19: =H17+H18 -> 3251 | I19: =I17+I18 -> 3588 | J19: =J17+J18 -> 4107 | ... V19: =V17+V18 -> 18485
B21: Cash and cash equivalents | C21: ='IFRS - Balance Sheet'!E12 -> 2200.663 | D21: ='IFRS - Balance Sheet'!F12 -> 2662.467 | E21: ='IFRS - Balance Sheet'!G12 -> 1996.725 | F21: ='IFRS - Balance Sheet'!H12 -> 2705.675 | G21: ='IFRS - Balance Sheet'!I12 -> 2968.622 | H21: ='IFRS - Balance Sheet'!J12 -> 3701.02 | I21: ='IFRS - Balance Sheet'!K12 -> 3692.793 | J21: ='IFRS - Balance Sheet'!L12 -> 4172.316 | ... V21: ='IFRS - Balance Sheet'!X12 -> 15003.643
B22: Securities - Financial assets at fair value through profit or loss | C22: ='IFRS - Balance Sheet'!E14 -> 4356.451 | D22: ='IFRS - Balance Sheet'!F14 -> 5343.289 | E22: ='IFRS - Balance Sheet'!G14 -> 4680.014 | F22: ='IFRS - Balance Sheet'!H14 -> 815.962 | G22: ='IFRS - Balance Sheet'!I14 -> 817.443 | H22: ='IFRS - Balance Sheet'!J14 -> 856.994 | I22: ='IFRS - Balance Sheet'!K14 -> 740.972 | J22: ='IFRS - Balance Sheet'!L14 -> 91.853 | ... V22: ='IFRS - Balance Sheet'!X14 -> 1059.923
B23: Securities - Financial assets at fair value through OCI | C23: ='IFRS - Balance Sheet'!E18 -> 0 | D23: ='IFRS - Balance Sheet'!F18 -> 348.518 | E23: ='IFRS - Balance Sheet'!G18 -> 1837.715 | F23: ='IFRS - Balance Sheet'!H18 -> 8163.428 | G23: ='IFRS - Balance Sheet'!I18 -> 9260.432 | H23: ='IFRS - Balance Sheet'!J18 -> 8850.741 | I23: ='IFRS - Balance Sheet'!K18 -> 8931.961 | J23: ='IFRS - Balance Sheet'!L18 -> 9947.138 | ... V23: ='IFRS - Balance Sheet'!X18 -> 12157.076
B24: Securities - Financial assets at amortized cost | C24: ='IFRS - Balance Sheet'!E25 -> 0 | D24: ='IFRS - Balance Sheet'!F25 -> 0 | E24: ='IFRS - Balance Sheet'!G25 -> 0 | F24: ='IFRS - Balance Sheet'!H25 -> 0 | G24: ='IFRS - Balance Sheet'!I25 -> 0 | H24: ='IFRS - Balance Sheet'!J25 -> 0 | I24: ='IFRS - Balance Sheet'!K25 -> 0 | J24: ='IFRS - Balance Sheet'!L25 -> 0 | ... V24: ='IFRS - Balance Sheet'!X25 -> 3141.504
B25: Compulsory and other deposits at central banks | C25: ='IFRS - Balance Sheet'!E22 -> 98.694 | D25: ='IFRS - Balance Sheet'!F22 -> 265.465 | E25: ='IFRS - Balance Sheet'!G22 -> 422.649 | F25: ='IFRS - Balance Sheet'!H22 -> 938.659 | G25: ='IFRS - Balance Sheet'!I22 -> 1333.427 | H25: ='IFRS - Balance Sheet'!J22 -> 1552.139 | I25: ='IFRS - Balance Sheet'!K22 -> 1860.438 | J25: ='IFRS - Balance Sheet'!L22 -> 2778.019 | ... V25: ='IFRS - Balance Sheet'!X22 -> 9537.788
B26: Other receivables | C26: ='IFRS - Balance Sheet'!E26 -> 0 | D26: ='IFRS - Balance Sheet'!F26 -> 0 | E26: ='IFRS - Balance Sheet'!G26 -> 0 | F26: ='IFRS - Balance Sheet'!H26 -> 50.349 | G26: ='IFRS - Balance Sheet'!I26 -> 285.632 | H26: ='IFRS - Balance Sheet'!J26 -> 374.188 | I26: ='IFRS - Balance Sheet'!K26 -> 381.782 | J26: ='IFRS - Balance Sheet'!L26 -> 521.67 | ... V26: ='IFRS - Balance Sheet'!X26 -> 1000.683
B27: Other financial assets | C27: ='IFRS - Balance Sheet'!E27 -> 19.896 | D27: ='IFRS - Balance Sheet'!F27 -> 24.899 | E27: ='IFRS - Balance Sheet'!G27 -> 39.228 | F27: ='IFRS - Balance Sheet'!H27 -> 18.493 | G27: ='IFRS - Balance Sheet'!I27 -> 49.739 | H27: ='IFRS - Balance Sheet'!J27 -> 61.136 | I27: ='IFRS - Balance Sheet'!K27 -> 75.591 | J27: ='IFRS - Balance Sheet'!L27 -> 478.283 | ... V27: ='IFRS - Balance Sheet'!X27 -> 148.777
B28: Derivatives | C28: ='IFRS - Balance Sheet'!E15 -> 0.034 | D28: ='IFRS - Balance Sheet'!F15 -> 5.845 | E28: ='IFRS - Balance Sheet'!G15 -> 89.543 | F28: ='IFRS - Balance Sheet'!H15 -> 101.318 | G28: ='IFRS - Balance Sheet'!I15 -> 209.439 | H28: ='IFRS - Balance Sheet'!J15 -> 109.934 | I28: ='IFRS - Balance Sheet'!K15 -> 39.552 | J28: ='IFRS - Balance Sheet'!L15 -> 41.485 | ... V28: ='IFRS - Balance Sheet'!X15 -> 80.748
B29: Collateral for credit card operations | C29: ='IFRS - Balance Sheet'!E16 -> 49.092 | D29: ='IFRS - Balance Sheet'!F16 -> 41.082 | E29: ='IFRS - Balance Sheet'!G16 -> 11.379 | F29: ='IFRS - Balance Sheet'!H16 -> 1.052 | G29: ='IFRS - Balance Sheet'!I16 -> 10.173 | H29: ='IFRS - Balance Sheet'!J16 -> 0.401 | I29: ='IFRS - Balance Sheet'!K16 -> 0.303 | J29: ='IFRS - Balance Sheet'!L16 -> 0.305 | ... V29: ='IFRS - Balance Sheet'!X16 -> 0
B30: Total Interest Earning Assets (IEA) | C30: =SUM(C21:C29,C19) -> 7355.83 | D30: =SUM(D21:D29,D19) -> 9711.565 | E30: =SUM(E21:E29,E19) -> 10492.253 | F30: =SUM(F21:F29,F19) -> 14832.936 | G30: =SUM(G21:G29,G19) -> 18010.907 | H30: =SUM(H21:H29,H19) -> 18757.553 | I30: =SUM(I21:I29,I19) -> 19311.392 | J30: =SUM(J21:J29,J19) -> 22138.069 | ... V30: =SUM(V21:V29,V19) -> 60615.142
B32: Average Balance
B33: Total Interest Earning Assets (IEA) | D33: =AVERAGE(C30:D30) -> 8533.6975 | E33: =AVERAGE(D30:E30) -> 10101.909 | F33: =AVERAGE(E30:F30) -> 12662.594 | G33: =AVERAGE(F30:G30) -> 16421.922 | H33: =AVERAGE(G30:H30) -> 18384.23 | I33: =AVERAGE(H30:I30) -> 19034.472 | J33: =AVERAGE(I30:J30) -> 20724.731 | K33: =AVERAGE(J30:K30) -> 21737.841 | ... V33: =AVERAGE(U30:V30) -> 58118.014
B35: Interest Income, Expense and Cost of Risk
B36: Credit Income | C36: ='Managerial P&L '!C12 -> 90.962 | D36: ='Managerial P&L '!D12 -> 130.2 | E36: ='Managerial P&L '!E12 -> 178.633 | F36: ='Managerial P&L '!F12 -> 203.839 | G36: ='Managerial P&L '!G12 -> 383.667 | H36: ='Managerial P&L '!H12 -> 471.951 | I36: ='Managerial P&L '!I12 -> 512.65 | J36: ='Managerial P&L '!J12 -> 578.803 | ... V36: ='Managerial P&L '!V12 -> 2777.963
B37: Float Income | C37: ='Managerial P&L '!C13 -> 36.477 | D37: ='Managerial P&L '!D13 -> 54.859 | E37: ='Managerial P&L '!E13 -> 116.687 | F37: ='Managerial P&L '!F13 -> 189.163 | G37: ='Managerial P&L '!G13 -> 235.85 | H37: ='Managerial P&L '!H13 -> 384.502 | I37: ='Managerial P&L '!I13 -> 482.546 | J37: ='Managerial P&L '!J13 -> 527.111 | ... V37: ='Managerial P&L '!V13 -> 1408.906
B38: Funding Cost | C38: ='Managerial P&L '!C17 -> -29.067 | D38: ='Managerial P&L '!D17 -> -53.886 | E38: ='Managerial P&L '!E17 -> -95.458 | F38: ='Managerial P&L '!F17 -> -159.158 | G38: ='Managerial P&L '!G17 -> -256.243 | H38: ='Managerial P&L '!H17 -> -376.357 | I38: ='Managerial P&L '!I17 -> -451.034 | J38: ='Managerial P&L '!J17 -> -395.735 | ... V38: ='Managerial P&L '!V17 -> -1349.973
B39: NII | C39: =SUM(C36:C38) -> 98.372 | D39: =SUM(D36:D38) -> 131.173 | E39: =SUM(E36:E38) -> 199.862 | F39: =SUM(F36:F38) -> 233.844 | G39: =SUM(G36:G38) -> 363.274 | H39: =SUM(H36:H38) -> 480.096 | I39: =SUM(I36:I38) -> 544.162 | J39: =SUM(J36:J38) -> 710.179 | ... V39: =SUM(V36:V38) -> 2836.896
B40: Cost of Credit | C40: ='Managerial P&L '!C18 -> -73.97 | D40: ='Managerial P&L '!D18 -> -86.018 | E40: ='Managerial P&L '!E18 -> -132.94 | F40: ='Managerial P&L '!F18 -> -217.49 | G40: ='Managerial P&L '!G18 -> -292.482 | H40: ='Managerial P&L '!H18 -> -369.635 | I40: ='Managerial P&L '!I18 -> -384.329 | J40: ='Managerial P&L '!J18 -> -426.999 | ... V40: ='Managerial P&L '!V18 -> -1313.223
B41: Risk-adjusted NII | C41: =C39+C40 -> 24.402 | D41: =D39+D40 -> 45.155 | E41: =E39+E40 -> 66.922 | F41: =F39+F40 -> 16.354 | G41: =G39+G40 -> 70.792 | H41: =H39+H40 -> 110.461 | I41: =I39+I40 -> 159.833 | J41: =J39+J40 -> 283.18 | ... V41: =V39+V40 -> 1523.673
B43: Margin (%)
B44: Risk-adjusted NIM (%) | D44: =D41/D33*4 -> 0.021165503 | E44: =E41/E33*4 -> 0.026498754 | F44: =F41/F33*4 -> 0.0051660819 | G44: =G41/G33*4 -> 0.017243293 | H44: =H41/H33*4 -> 0.024033859 | I44: =I41/I33*4 -> 0.033588112 | J44: =J41/J33*4 -> 0.054655476 | K44: =K41/K33*4 -> 0.064682045 | ... V44: =V41/V33*4 -> 0.10486752
B46: Efficiency Ratio (%)
B47: Operating Expenses | C47: =-'Managerial P&L '!C24 -> 167.585 | D47: =-'Managerial P&L '!D24 -> 171.575 | E47: =-'Managerial P&L '!E24 -> 243.681 | F47: =-'Managerial P&L '!F24 -> 307.914 | G47: =-'Managerial P&L '!G24 -> 356.503 | H47: =-'Managerial P&L '!H24 -> 342.734 | I47: =-'Managerial P&L '!I24 -> 389.448 | J47: =-'Managerial P&L '!J24 -> 756.441 | ... V47: =-'Managerial P&L '!V24 -> 652.635
B48: Total Revenue | C48: ='Managerial P&L '!C11 -> 247.185 | D48: ='Managerial P&L '!D11 -> 338.62 | E48: ='Managerial P&L '!E11 -> 483.044 | F48: ='Managerial P&L '!F11 -> 591.206 | G48: ='Managerial P&L '!G11 -> 879.075 | H48: ='Managerial P&L '!H11 -> 1163.24 | I48: ='Managerial P&L '!I11 -> 1316.162 | J48: ='Managerial P&L '!J11 -> 1463.394 | ... V48: ='Managerial P&L '!V11 -> 4857.306
B49: Funding Cost | C49: ='Managerial P&L '!C17 -> -29.067 | D49: ='Managerial P&L '!D17 -> -53.886 | E49: ='Managerial P&L '!E17 -> -95.458 | F49: ='Managerial P&L '!F17 -> -159.158 | G49: ='Managerial P&L '!G17 -> -256.243 | H49: ='Managerial P&L '!H17 -> -376.357 | I49: ='Managerial P&L '!I17 -> -451.034 | J49: ='Managerial P&L '!J17 -> -395.735 | ... V49: ='Managerial P&L '!V17 -> -1349.973
B50: Transaction Cost | C50: ='Managerial P&L '!C19 -> -28.377 | D50: ='Managerial P&L '!D19 -> -32.148 | E50: ='Managerial P&L '!E19 -> -30.335 | F50: ='Managerial P&L '!F19 -> -34.217 | G50: ='Managerial P&L '!G19 -> -36.182 | H50: ='Managerial P&L '!H19 -> -50.275 | I50: ='Managerial P&L '!I19 -> -45.822 | J50: ='Managerial P&L '!J19 -> -51.921 | ... V50: ='Managerial P&L '!V19 -> -99.019
B51: Revenue-Based Taxes | C51: ='Managerial P&L '!C20 -> -1.516 | D51: ='Managerial P&L '!D20 -> -1.456 | E51: ='Managerial P&L '!E20 -> -2.244 | F51: ='Managerial P&L '!F20 -> -3.531 | G51: ='Managerial P&L '!G20 -> -5.285 | H51: ='Managerial P&L '!H20 -> -47.142 | I51: ='Managerial P&L '!I20 -> -31.125 | J51: ='Managerial P&L '!J20 -> -38.676 | ... V51: ='Managerial P&L '!V20 -> -134.025
B52: Efficiency Ratio (%) | C52: =C47/SUM(C48:C51) -> 0.890344 | D52: =D47/SUM(D48:D51) -> 0.68321188 | E52: =E47/SUM(E48:E51) -> 0.68641182 | F52: =F47/SUM(F48:F51) -> 0.78091301 | G52: =G47/SUM(G48:G51) -> 0.61321717 | H52: =H47/SUM(H48:H51) -> 0.49710065 | I52: =I47/SUM(I48:I51) -> 0.49410986 | J52: =J47/SUM(J48:J51) -> 0.77419959 | ... V52: =V47/SUM(V48:V51) -> 0.19932114
B54: Liquidity Position
B55: Credit Card Receivables (Gross) | C55: ='IFRS - Credit operations'!E12 -> 2994.691 | D55: ='IFRS - Credit operations'!F12 -> 4087.424 | E55: ='IFRS - Credit operations'!G12 -> 4367.874 | F55: ='IFRS - Credit operations'!H12 -> 5162.153 | G55: ='IFRS - Credit operations'!I12 -> 6803.234 | H55: ='IFRS - Credit operations'!J12 -> 7163.201 | I55: ='IFRS - Credit operations'!K12 -> 7799.6 | J55: ='IFRS - Credit operations'!L12 -> 9266.225 | ... V55: ='IFRS - Credit operations'!X12 -> 21751.226
B56: Loan to Customers (Gross) | C56: ='IFRS - Credit operations'!E26 -> 303.897 | D56: ='IFRS - Credit operations'!F26 -> 592.454 | E56: ='IFRS - Credit operations'!G26 -> 903.061 | F56: ='IFRS - Credit operations'!H26 -> 1392.35 | G56: ='IFRS - Credit operations'!I26 -> 2009.494 | H56: ='IFRS - Credit operations'!J26 -> 1952.511 | I56: ='IFRS - Credit operations'!K26 -> 1907.405 | J56: ='IFRS - Credit operations'!L26 -> 1976.499 | ... V56: ='IFRS - Credit operations'!X26 -> 10915.453
B57: Payables to network | C57: =-'IFRS - Balance Sheet'!E43 -> -2982.547 | D57: =-'IFRS - Balance Sheet'!F43 -> -3990.411 | E57: =-'IFRS - Balance Sheet'!G43 -> -4127.691 | F57: =-'IFRS - Balance Sheet'!H43 -> -4882.159 | G57: =-'IFRS - Balance Sheet'!I43 -> -5920.795 | H57: =-'IFRS - Balance Sheet'!J43 -> -5930.966 | I57: =-'IFRS - Balance Sheet'!K43 -> -5894.436 | J57: =-'IFRS - Balance Sheet'!L43 -> -7054.783 | ... V57: =-'IFRS - Balance Sheet'!X43 -> -13633.949
B58: Net Credit Portfolio | C58: =SUM(C55:C57) -> 316.041 | D58: =SUM(D55:D57) -> 689.467 | E58: =SUM(E55:E57) -> 1143.244 | F58: =SUM(F55:F57) -> 1672.344 | G58: =SUM(G55:G57) -> 2891.933 | H58: =SUM(H55:H57) -> 3184.746 | I58: =SUM(I55:I57) -> 3812.569 | J58: =SUM(J55:J57) -> 4187.941 | ... V58: =SUM(V55:V57) -> 19032.73
B59: Deposits | C59: ='IFRS - Balance Sheet'!E42 -> 5461.652 | D59: ='IFRS - Balance Sheet'!F42 -> 7505.684 | E59: ='IFRS - Balance Sheet'!G42 -> 8089.835 | F59: ='IFRS - Balance Sheet'!H42 -> 9667.3 | G59: ='IFRS - Balance Sheet'!I42 -> 12596.927 | H59: ='IFRS - Balance Sheet'!J42 -> 13293.235 | I59: ='IFRS - Balance Sheet'!K42 -> 14040.157 | J59: ='IFRS - Balance Sheet'!L42 -> 15808.541 | ... V59: ='IFRS - Balance Sheet'!X42 -> 41925.101
B60: Financial Bills | C60: =55792613/1000000 -> 55.792613 | D60: 0 | E60: 0 | F60: 0 | G60: 0 | H60: 0 | I60: 0 | J60: 0 | K60: 0 | L60: =23074/1000 -> 23.074 | M60: =194688/1000 -> 194.688 | N60: =216068/1000 -> 216.068 | O60: =485178/1000 -> 485.178 | P60: =953829/1000 -> 953.829 | Q60: =1202396/1000 -> 1202.396 | R60: =1178603/1000 -> 1178.603 | S60: =1355369/1000 -> 1355.369 | T60: =1729675/1000 -> 1729.675 | U60: =2050148/1000 -> 2050.148 | V60: =2529590/1000 -> 2529.59
B61: Compulsory Deposits | C61: =-98694277.12/1000000 -> -98.694277 | D61: =-265464969/1000000 -> -265.46497 | E61: =-422648606/1000000 -> -422.64861 | F61: =-819794/1000 -> -819.794 | G61: =-1228639918.7/1000000 -> -1228.6399 | H61: =-1436370533/1000000 -> -1436.3705 | I61: =-1623251502.12/1000000 -> -1623.2515 | J61: =-2026516/1000 -> -2026.516 | K61: =-2159408/1000 -> -2159.408 | L61: =-2486301/1000 -> -2486.301 | M61: =-2778024/1000 -> -2778.024 | N61: =-3342894/1000 -> -3342.894 | O61: =-3394981/1000 -> -3394.981 | P61: =-3420494/1000 -> -3420.494 | Q61: =-3928473/1000 -> -3928.473 | R61: -3833.67 | S61: =-4067215/1000 -> -4067.215 | T61: =-4658054/1000 -> -4658.054 | U61: =-5182493/1000 -> -5182.493 | V61: =-5687184/1000 -> -5687.184
B62: Total Available Funding | C62: =SUM(C59:C61) -> 5418.7503 | D62: =SUM(D59:D61) -> 7240.219 | E62: =SUM(E59:E61) -> 7667.1864 | F62: =SUM(F59:F61) -> 8847.506 | G62: =SUM(G59:G61) -> 11368.287 | H62: =SUM(H59:H61) -> 11856.864 | I62: =SUM(I59:I61) -> 12416.906 | J62: =SUM(J59:J61) -> 13782.025 | ... V62: =SUM(V59:V61) -> 38767.507
B63: Net Credit Portfolio / Available Funding | C63: =C58/C62 -> 0.058323595 | D63: =D58/D62 -> 0.095227368 | E63: =E58/E62 -> 0.14910867 | F63: =F58/F62 -> 0.18901869 | G63: =G58/G62 -> 0.25438599 | H63: =H58/H62 -> 0.26859934 | I63: =I58/I62 -> 0.30704663 | J63: =J58/J62 -> 0.30386979 | ... V63: =V58/V62 -> 0.49094542

Sheet Operating figures
B2: Nu Holdings Ltd.
B3: Operating Figures
B4: Amounts in billion of US$, unless otherwise noted
B5: Back to Contents
C9: 43921 | D9: 44012 | E9: 44104 | F9: 44196 | G9: 44286 | H9: 44377 | I9: 44469 | J9: 44561 | K9: 44651 | L9: 44742 | M9: 44834 | N9: 44926 | O9: 45016 | P9: 30/06/2023 | Q9: 30/09/2023 | R9: 31/12/2023 | S9: 31/03/2024 | T9: 30/06/2024 | U9: 30/09/2024 | V9: 31/12/2024 | W9: 31/03/2025 | X9: 30/06/2025 | Y9: 30/09/2025 | Z9: 31/12/2025
B10: Number of customers (# MM)
B11: Brazil | C11: 23.5 | D11: 26.1 | E11: 29.7 | F11: 33.2 | G11: 36.9 | H11: 41.3 | I11: 47.3 | J11: 52.4 | K11: 57.3 | L11: 62.3 | M11: 66.9 | N11: 70.9 | O11: 75.3 | P11: 79.4 | Q11: 84 | R11: 87.9 | S11: 91.8 | T11: 95.5 | U11: 98.8 | V11: 101.8 | W11: 104.6 | X11: 107.3 | Y11: 110.1 | Z11: 112.7
B12: Individual | C12: 23.3 | D12: 25.8 | E12: 29.3 | F12: 32.7 | G12: 36.3 | H12: 40.5 | I12: 46.2 | J12: 51 | K12: 55.7 | L12: 60.3 | M12: 64.6 | N12: 68.4 | O12: 72.6 | P12: 76.3 | Q12: 80.6 | R12: 84.3 | S12: 87.8 | T12: 91.3 | U12: 94.3 | V12: 97.1 | W12: 99.7 | X12: 102.1 | Y12: 104.5 | Z12: 106.8
B13: SME | C13: 0.2 | D13: 0.3 | E13: 0.4 | F13: 0.5 | G13: 0.6 | H13: 0.8 | I13: 1.1 | J13: 1.4 | K13: 1.6 | L13: 2 | M13: 2.3 | N13: 2.5 | O13: 2.7 | P13: 3.1 | Q13: 3.4 | R13: 3.6 | S13: 4 | T13: 4.2 | U13: 4.5 | V13: 4.7 | W13: 4.9 | X13: 5.2 | Y13: 5.6 | Z13: 5.9
B14: Mexico | C14: 0 | D14: 0 | E14: 0 | F14: 0.1 | G14: 0.2 | H14: 0.4 | I14: 0.7 | J14: 1.4 | K14: 2.1 | L14: 2.7 | M14: 3 | N14: 3.2 | O14: 3.2 | P14: 3.6 | Q14: 4.3 | R14: 5.2 | S14: 6.6 | T14: 7.8 | U14: 8.9 | V14: 10 | W14: 11 | X14: 12 | Y14: 13.1 | Z14: 14.1
B15: Colombia | C15: 0 | D15: 0 | E15: 0 | F15: 0 | G15: 0 | H15: 0 | I15: 0 | J15: 0.1 | K15: 0.2 | L15: 0.3 | M15: 0.4 | N15: 0.6 | O15: 0.6 | P15: 0.7 | Q15: 0.8 | R15: 0.8 | S15: 0.9 | T15: 1.3 | U15: 2 | V15: 2.5 | W15: 2.9 | X15: 3.4 | Y15: 3.8 | Z15: 4.2
B17: Number of active customers (# MM) - Nu Holdings
B18: Total | C18: 14 | D18: 15.7 | E18: 18.6 | F18: 21.8 | G18: 25.5 | H18: 29.9 | I18: 35.2 | J18: 41.1 | K18: 46.5 | L18: 52.3 | M18: 57.4 | N18: 61.2 | O18: 64.9 | P18: 68.8 | Q18: 73.8 | R18: 78 | S18: 82.6 | T18: 87.2 | U18: 91.7 | V18: 94.9 | W18: 98.7 | X18: 102.2 | Y18: 105.9 | Z18: 109.3
B19: Credit Card (Consumer + SME) | C19: 11 | D19: 11.4 | E19: 12.6 | F19: 15.3 | G19: 18 | H19: 20.6 | I19: 24.2 | J19: 26.8 | K19: 29.9 | L19: 32.6 | M19: 35.8 | N19: 38.1 | O19: 40.2 | P19: 42.3 | Q19: 44.9 | R19: 46.8 | S19: 48.4 | T19: 49.6 | U19: 50.4 | V19: 53 | W19: 54.6 | X19: 55 | Y19: 56.8 | Z19: 57.6
B20: Unsecured Lending (Consumer + SME) | C20: 0.1 | D20: 0.1 | E20: 0.1 | F20: 0.3 | G20: 0.5 | H20: 0.9 | I20: 1.4 | J20: 2.3 | K20: 2.7 | L20: 4.2 | M20: 5.3 | N20: 5.2 | O20: 6.1 | P20: 6.7 | Q20: 7.3 | R20: 7.1 | S20: 8 | T20: 8.7 | U20: 9.8 | V20: 11.1 | W20: 12.4 | X20: 13.6 | Y20: 14.2 | Z20: 14.4
B22: Payment volume (US$ Bn)
B23: Total PV | C23: 5.1 | D23: 4.1 | E23: 5.7 | F23: 7.6 | G23: 7.5 | H23: 9.9 | I23: 12.1 | J23: 14.4 | K23: 15.9 | L23: 20 | M23: 21.2 | N23: 23.8 | O23: 23.3 | P23: 26.3 | Q23: 28.9 | R23: 32.6 | S23: 31.1 | T23: 31.3 | U23: 30.9 | V23: 32.2 | W23: 30.4 | X23: 33.3 | Y23: 36.5 | Z23: 41.6
B24: Credit Card | C24: 4.6 | D24: 3.6 | E24: 4.6 | F24: 5.8 | G24: 5.6 | H24: 7.2 | I24: 8.4 | J24: 9.6 | K24: 10.6 | L24: 13.1 | M24: 13.6 | N24: 15.1 | O24: 15.1 | P24: 17.1 | Q24: 18.7 | R24: 20.7 | S24: 20.2 | T24: 20.3 | U24: 20 | V24: 20.6 | W24: 19.8 | X24: 21.9 | Y24: 24.2 | Z24: 27.7
B25: Debit Card | C25: 0.5 | D25: 0.5 | E25: 1.1 | F25: 1.8 | G25: 1.8 | H25: 2.7 | I25: 3.7 | J25: 4.8 | K25: 5.3 | L25: 7 | M25: 7.6 | N25: 8.7 | O25: 8.2 | P25: 9.2 | Q25: 10.2 | R25: 11.9 | S25: 10.9 | T25: 11 | U25: 10.9 | V25: 11.6 | W25: 10.6 | X25: 11.4 | Y25: 12.3 | Z25: 13.9
B27: Number of employees (# '000)
B28: Total | C28: 2.6 | D28: 2.7 | E28: 2.7 | F28: 2.9 | G28: 3.3 | H28: 4.5 | I28: 5.4 | J28: 6.1 | K28: 6.9 | L28: 7.7 | M28: 8 | N28: 8 | O28: 7.8 | P28: 7.6 | Q28: 7.6 | R28: 7.7 | S28: 8 | T28: 8.3 | U28: 8.6 | V28: 8.7 | W28: 8.9 | X28: 9.3 | Y28: 9.6 | Z28: 10

Sheet NPLs
B2: Nu Holdings Ltd.
B3: Non-Performing Loans (NPLs)
B4: %
B5: Back to Contents
C9: 43921 | D9: 44012 | E9: 44104 | F9: 44196 | G9: 44286 | H9: 44377 | I9: 44469 | J9: 44561 | K9: 44651 | L9: 44742 | M9: 44834 | N9: 44926 | O9: 45016 | P9: 30/06/2023 | Q9: 30/09/2023 | R9: 31/12/2023 | S9: 31/03/2024 | T9: 30/06/2024 | U9: 30/09/2024 | V9: 31/12/2024 | W9: 31/03/2025 | X9: 30/06/2025 | Y9: 30/09/2025 | Z9: 31/12/2025
B10: Nu Holdings Credit Portfolio
B12: 15-90 days NPL | C12: 0.035 | D12: 0.022 | E12: 0.012 | F12: 0.013 | G12: 0.025 | H12: 0.022 | I12: 0.024 | J12: 0.027 | K12: 0.038 | L12: 0.039 | M12: 0.045 | N12: 0.041 | O12: 0.047 | P12: 0.045 | Q12: 0.044 | R12: 0.042 | S12: 0.051 | T12: 0.047 | U12: 0.045 | V12: 0.042 | W12: 0.048 | X12: 0.045 | Y12: 0.043 | Z12: 0.041
B13: 90+ NPL | C13: 0.05 | D13: 0.062 | E13: 0.053 | F13: 0.037 | G13: 0.029 | H13: 0.028 | I13: 0.031 | J13: 0.031 | K13: 0.034 | L13: 0.04 | M13: 0.046 | N13: 0.051 | O13: 0.053 | P13: 0.058 | Q13: 0.059 | R13: 0.06 | S13: 0.061 | T13: 0.068 | U13: 0.07 | V13: 0.067 | W13: 0.064 | X13: 0.065 | Y13: 0.067 | Z13: 0.066

Sheet FX Rates
B2: Nu Holdings Ltd.
B3: FX Rates
B5: Back to Contents
C9: 44286 | D9: 44377 | E9: 44469 | F9: 44561 | G9: 44651 | H9: 44742 | I9: 44834 | J9: 44926 | K9: 45016 | L9: 30/06/2023 | M9: 30/09/2023 | N9: 31/12/2023 | O9: 31/03/2024 | P9: 30/06/2024 | Q9: 30/09/2024 | R9: 31/12/2024 | S9: 31/03/2025 | T9: 30/06/2025 | U9: 30/09/2025 | V9: 31/12/2025
B10: FX Rates
B12: BRL/USD Average | C12: 5.4856 | D12: 5.2893 | E12: 5.2319 | F12: 5.5851 | G12: 5.225 | H12: 4.9273 | I12: 5.2464 | J12: 5.2588 | K12: 5.1924 | L12: 4.9449 | M12: 4.8851 | N12: 4.9576 | O12: 4.9515 | P12: 5.2154 | Q12: 5.5463 | R12: 5.8402 | S12: 5.8487 | T12: 5.6625 | U12: 5.4493 | V12: 5.3988
B13: BRL/USD End of the Period | C13: 5.6337 | D13: 4.9696 | E13: 5.4429 | F13: 5.5758 | G13: 4.7417 | H13: 5.257 | I13: 5.4155 | J13: 5.2804 | K13: 5.0631 | L13: 4.7854 | M13: 5.0341 | N13: 4.8572 | O13: 5.0145 | P13: 5.5941 | Q13: 5.45 | R13: 6.1736 | S13: 5.7058 | T13: 5.4316 | U13: 5.3217 | V13: 5.4956

Sheet IFRS - Statement of Income
B2: Nu Holdings Ltd.
B3: Consolidated Statement of Profit or Loss - Quarter
B4: Amounts in million of US$, except earnings (loss) per share
B5: Back to Contents
C8: 3-MONTH PERIOD ENDED
C9: 43921 | D9: 44012 | E9: 44104 | F9: 44196 | G9: 44286 | H9: 44377 | I9: 44469 | J9: 44561 | K9: 44651 | L9: 44742 | M9: 44834 | N9: 44926 | O9: 45016 | P9: 45107 | Q9: 45199 | R9: 45291 | S9: 45382 | T9: 45473 | U9: 45565 | V9: 45657 | W9: 45747 | X9: 45838 | Y9: 45930 | Z9: 46022
C10: US$ | D10: US$ | E10: US$ | F10: US$ | G10: US$ | H10: US$ | I10: US$ | J10: US$ | K10: US$ | L10: US$ | M10: US$ | N10: US$ | O10: US$ | P10: US$ | Q10: US$ | R10: US$ | S10: US$ | T10: US$ | U10: US$ | V10: US$ | W10: US$ | X10: US$ | Y10: US$ | Z10: US$
B11: Interest income and gains net of losses on financial instruments | C11: 131.243 | D11: 91.884 | E11: 70.14 | F11: 89.655 | G11: 127.345 | H11: 184.893 | I11: 294.958 | J11: 439.55 | K11: 619.443 | L11: 853.013 | M11: 987.248 | N11: 1095.509 | O11: 1255.454 | P11: 1500.225 | Q11: 1732.699 | R11: 1951.334 | S11: 2280.248 | T11: 2383.307 | U11: 2473.807 | V11: 2493.681 | W11: 2732.136 | X11: 3128.743 | Y11: 3577.478 | Z11: 3996.326
B12: Fee and commission income | C12: 84.912 | D12: 70.443 | E12: 85.946 | F12: 112.91 | G12: 117.718 | H12: 151.195 | I12: 185.949 | J12: 196.415 | K12: 257.824 | L12: 304.548 | M12: 319.619 | N12: 355.027 | O12: 363.213 | P12: 368.415 | Q12: 404.059 | R12: 453.577 | S12: 455.653 | T12: 465.384 | U12: 469.381 | V12: 495.614 | W12: 515.553 | X12: 539.727 | Y12: 595.238 | Z12: 689.54
B13: Total revenue | C13: 216.155 | D13: 162.327 | E13: 156.086 | F13: 202.565 | G13: 245.063 | H13: 336.088 | I13: 480.907 | J13: 635.965 | K13: 877.267 | L13: 1157.561 | M13: 1306.867 | N13: 1450.536 | O13: 1618.667 | P13: 1868.64 | Q13: 2136.758 | R13: 2404.911 | S13: 2735.901 | T13: 2848.691 | U13: 2943.188 | V13: 2989.295 | W13: 3247.689 | X13: 3668.47 | Y13: 4172.716 | Z13: 4685.866
B15: Interest and other financial expenses | C15: -33.23 | D15: -25.321 | E15: -23.984 | F15: -31.389 | G15: -31.743 | H15: -57.236 | I15: -101.393 | J15: -176.972 | K15: -273.003 | L15: -407.5 | M15: -459.889 | N15: -407.511 | O15: -440.212 | P15: -453.426 | Q15: -537.649 | R15: -605.638 | S15: -660.715 | T15: -665.191 | U15: -760.959 | V15: -747.994 | W15: -896.204 | X15: -1029.989 | Y15: -1275.711 | Z15: -1376.776
B16: Transactional expenses | C16: -33.136 | D16: -22.604 | E16: -31.91 | F16: -39.165 | G16: -26.349 | H16: -29.782 | I16: -28.56 | J16: -32.428 | K16: -34.448 | L16: -48.036 | M16: -44.475 | N16: -49.468 | O16: -52.778 | P16: -42.797 | Q16: -56.774 | R16: -63.581 | S16: -62.948 | T16: -64.31 | U16: -59.454 | V16: -73.612 | W16: -58.488 | X16: -78.311 | Y16: -104.99 | Z16: -124.394
B17: Expected credit loss | C17: -61.825 | D17: -19.019 | E17: -32.939 | F17: -55.702 | G17: -71.294 | H17: -82.668 | I17: -127.005 | J17: -199.676 | K17: -275.722 | L17: -338.492 | M17: -375.474 | N17: -415.223 | O17: -474.795 | P17: -590.434 | Q17: -627.506 | R17: -592.483 | S17: -830.719 | T17: -759.765 | U17: -774.144 | V17: -804.355 | W17: -973.544 | X17: -1012.192 | Y17: -977.483 | Z17: -1241.657
B18: Total cost of financial and transactional services provided | C18: -128.191 | D18: -66.944 | E18: -88.833 | F18: -126.256 | G18: -129.386 | H18: -169.686 | I18: -256.958 | J18: -409.076 | K18: -583.173 | L18: -794.028 | M18: -879.838 | N18: -872.202 | O18: -967.785 | P18: -1086.657 | Q18: -1221.929 | R18: -1261.702 | S18: -1554.382 | T18: -1489.266 | U18: -1594.557 | V18: -1625.961 | W18: -1928.236 | X18: -2120.492 | Y18: -2358.184 | Z18: -2742.827
B20: Gross profit | C20: 87.964 | D20: 95.383 | E20: 67.253 | F20: 76.309 | G20: 115.677 | H20: 166.402 | I20: 223.949 | J20: 226.889 | K20: 294.094 | L20: 363.533 | M20: 427.029 | N20: 578.334 | O20: 650.882 | P20: 781.983 | Q20: 914.829 | R20: 1143.209 | S20: 1181.519 | T20: 1359.425 | U20: 1348.631 | V20: 1363.334 | W20: 1319.453 | X20: 1547.978 | Y20: 1814.532 | Z20: 1943.039
B22: Operating (expenses) income | C22: 0 | D22: 0 | E22: 0 | F22: 0 | G22: 0 | H22: 0 | I22: 0 | J22: 0 | K22: 0 | L22: 0 | M22: 0 | N22: 0 | O22: 0 | P22: 0 | Q22: 0 | R22: 0 | S22: 0 | T22: 0 | U22: 0 | V22: 0 | W22: 0 | X22: 0 | Y22: 0 | Z22: 0
B23: Customer support and operations | C23: -40.099 | D23: -26.427 | E23: -28.93 | F23: -28.494 | G23: -32.13 | H23: -40.968 | I23: -51.649 | J23: -65.762 | K23: -61.571 | L23: -77.703 | M23: -90.249 | N23: -105.84 | O23: -107.815 | P23: -113.309 | Q23: -127.295 | R23: -139.663 | S23: -150.612 | T23: -162.917 | U23: -135.196 | V23: -155.918 | W23: -151.475 | X23: -161.434 | Y23: -174.843 | Z23: -164.008
B24: General and administrative expenses (G&A) | C24: -70.624 | D24: -56.979 | E24: -56.788 | F24: -81.633 | G24: -115.848 | H24: -122.295 | I24: -166.527 | J24: -224.231 | K24: -245.108 | L24: -229.505 | M24: -261.778 | N24: -596.876 | O24: -236.881 | P24: -256.408 | Q24: -264.264 | R24: -284.737 | S24: -326.052 | T24: -326.555 | U24: -284.706 | V24: -318.773 | W24: -289.823 | X24: -341.253 | Y24: -349.262 | Z24: -440.122
B25: G&A - Contingent share award (CSA) termination | C25: 0 | D25: 0 | E25: 0 | F25: 0 | G25: 0 | H25: 0 | I25: 0 | J25: 0 | K25: 0 | L25: 0 | M25: 0 | N25: -355.573 | O25: 0 | P25: 0 | Q25: 0 | R25: 0 | S25: 0 | T25: 0 | U25: 0 | V25: 0 | W25: 0 | X25: 0 | Y25: 0 | Z25: 0
... B50: Weighted average number of outstanding shares – Diluted (in thousands of shares) | C50: 1296.708 | D50: 4170.423 | E50: 1320.606 | F50: 1315.578 | G50: 1347.325 | H50: 1366.612 | I50: 1423.876 | J50: 2270.693 | K50: 4660.405 | L50: 4670.972 | M50: 4824.031 | N50: 4692.626 | O50: 4818.2 | P50: 4843.835 | Q50: 4856.845 | R50: 4862.753 | S50: 4886.361 | T50: 4880.953 | U50: 4889.409 | V50: 4894.072 | W50: 4892.628 | X50: 4899.768 | Y50: 4905.133 | Z50: 4907.352

Sheet IFRS - Balance Sheet
B2: Nu Holdings Ltd.
B3: Consolidated Statement of Financial Position
B4: Amounts in million of US$
B5: Back to Contents
C9: 43830 | D9: 44196 | E9: 44286 | F9: 44377 | G9: 44469 | H9: 44561 | I9: 44651 | J9: 44742 | K9: 44834 | L9: 44926 | M9: 45016 | N9: 45107 | O9: 45199 | P9: 45291 | Q9: 45382 | R9: 45473 | S9: 45565 | T9: 45657 | U9: 45747 | V9: 45838 | W9: 45930 | X9: 46022
C10: US$ | D10: US$ | E10: US$ | F10: US$ | G10: US$ | H10: US$ | I10: US$ | J10: US$ | K10: US$ | L10: US$ | M10: US$ | N10: US$ | O10: US$ | P10: US$ | Q10: US$ | R10: US$ | S10: US$ | T10: US$ | U10: US$ | V10: US$ | W10: US$ | X10: US$
B11: Assets
B12: Cash and cash equivalents | C12: 1246.566 | D12: 2343.78 | E12: 2200.663 | F12: 2662.467 | G12: 1996.725 | H12: 2705.675 | I12: 2968.622 | J12: 3701.02 | K12: 3692.793 | L12: 4172.316 | M12: 4310.496 | N12: 6175.049 | O12: 3213.627 | P12: 5923.44 | Q12: 6033.658 | R12: 8530.383 | S12: 7645.754 | T12: 9185.742 | U12: 10284.007 | V12: 13269.017 | W12: 12895.785 | X12: 15003.643
B13: Financial assets at fair value through profit or loss | C13: 2400.691 | D13: 4378.118 | E13: 4405.577 | F13: 5390.216 | G13: 4780.936 | H13: 918.332 | I13: 1037.055 | J13: 967.329 | K13: 780.827 | L13: 133.643 | M13: 109.033 | N13: 182.769 | O13: 119.176 | P13: 389.875 | Q13: 646.131 | R13: 841.256 | S13: 314.885 | T13: 741.042 | U13: 462.853 | V13: 541.468 | W13: 1492.713 | X13: 1140.671
B14: Securities | C14: 2237.673 | D14: 4287.277 | E14: 4356.451 | F14: 5343.289 | G14: 4680.014 | H14: 815.962 | I14: 817.443 | J14: 856.994 | K14: 740.972 | L14: 91.853 | M14: 94.038 | N14: 156.233 | O14: 103.319 | P14: 368.574 | Q14: 624.731 | R14: 813.39 | S14: 119.281 | T14: 665.242 | U14: 335.846 | V14: 397.542 | W14: 1204.982 | X14: 1059.923
B15: Derivatives | C15: 0.241 | D15: 0.08 | E15: 0.034 | F15: 5.845 | G15: 89.543 | H15: 101.318 | I15: 209.439 | J15: 109.934 | K15: 39.552 | L15: 41.485 | M15: 14.686 | N15: 26.223 | O15: 15.541 | P15: 20.981 | Q15: 21.076 | R15: 27.538 | S15: 195.272 | T15: 75.464 | U15: 126.667 | V15: 143.583 | W15: 287.731 | X15: 80.748
B16: Collateral for credit card operations | C16: 162.777 | D16: 90.761 | E16: 49.092 | F16: 41.082 | G16: 11.379 | H16: 1.052 | I16: 10.173 | J16: 0.401 | K16: 0.303 | L16: 0.305 | M16: 0.309 | N16: 0.313 | O16: 0.316 | P16: 0.32 | Q16: 0.324 | R16: 0.328 | S16: 0.332 | T16: 0.336 | U16: 0.34 | V16: 0.343 | W16: 0 | X16: 0
B17: Financial assets at fair value through other comprehensive income | C17: 0 | D17: 0 | E17: 0 | F17: 348.518 | G17: 1837.715 | H17: 8163.428 | I17: 9260.432 | J17: 8850.741 | K17: 8931.961 | L17: 9947.138 | M17: 7916.143 | N17: 7479.797 | O17: 8605.769 | P17: 8805.745 | Q17: 8801.925 | R17: 8156.073 | S17: 11019.2 | T17: 9913.517 | U17: 9901.753 | V17: 10830.505 | W17: 11615.169 | X17: 12157.076
B18: Securities | C18: 0 | D18: 0 | E18: 0 | F18: 348.518 | G18: 1837.715 | H18: 8163.428 | I18: 9260.432 | J18: 8850.741 | K18: 8931.961 | L18: 9947.138 | M18: 7916.143 | N18: 7479.797 | O18: 8605.769 | P18: 8805.745 | Q18: 8801.925 | R18: 8156.073 | S18: 11019.2 | T18: 9913.517 | U18: 9901.753 | V18: 10830.505 | W18: 11615.169 | X18: 12157.076
B19: Financial assets at amortized cost | C19: 2923.676 | D19: 3150.013 | E19: 3172.369 | F19: 4634.392 | G19: 5335.867 | H19: 6982.835 | I19: 9571.139 | J19: 10141.709 | K19: 10908.864 | L19: 13684.484 | M19: 15029.584 | N19: 17135.46 | O19: 20857.39 | P19: 24988.919 | Q19: 25309.564 | R19: 24262.748 | S19: 26240.578 | T19: 26701.505 | U19: 29605.15 | V19: 33707.492 | W19: 37659.426 | X19: 41518.114
B20: Credit card receivables | C20: 2786.524 | D20: 2908.907 | E20: 2787.813 | F20: 3819.891 | G20: 4061.505 | H20: 4780.52 | I20: 6234.824 | J20: 6478.47 | K20: 6987.948 | L20: 8233.072 | M20: 9158.452 | N20: 10387.713 | O20: 10495.524 | P20: 12414.133 | Q20: 12796.677 | R20: 12027.336 | S20: 12689.21 | T20: 12259.276 | U20: 13540.738 | V20: 15129.529 | W20: 16772.45 | X20: 18267.904
B21: Loans to customers | C21: 58.024 | D21: 174.694 | E21: 264.542 | F21: 519.686 | G21: 792.736 | H21: 1194.814 | I21: 1667.517 | J21: 1675.776 | K21: 1603.105 | L21: 1673.44 | M21: 2020.191 | N21: 2433.209 | O21: 2689.978 | P21: 3202.334 | Q21: 3863.812 | R21: 4008.201 | S21: 4939.376 | T21: 5321.885 | U21: 6812.656 | V21: 7870.252 | W21: 8981.758 | X21: 9421.458
B22: Compulsory and other deposits at central banks | C22: 0 | D22: 43.542 | E22: 98.694 | F22: 265.465 | G22: 422.649 | H22: 938.659 | I22: 1333.427 | J22: 1552.139 | K22: 1860.438 | L22: 2778.019 | M22: 2671.668 | N22: 2826.879 | O22: 5849.454 | P22: 7447.483 | Q22: 7005.946 | R22: 6665.907 | S22: 6800.215 | T22: 6743.336 | U22: 7375.537 | V22: 8210.232 | W22: 8166.047 | X22: 9537.788
B23: Interbank transactions | C23: 0.091 | D23: 0 | E23: 1.424 | F23: 4.451 | G23: 19.749 | H23: 0 | I23: 0 | J23: 0 | K23: 0 | L23: 0 | M23: 0 | N23: 0 | O23: 0 | P23: 0 | Q23: 0 | R23: 0 | S23: 0 | T23: 0 | U23: 0 | V23: 0 | W23: 0 | X23: 0
C24: 0 | D24: 0 | E24: 0 | F24: 0 | G24: 0 | H24: 0 | I24: 0 | J24: 0 | K24: 0 | L24: 0 | M24: 0 | N24: 0 | O24: 0 | P24: 0 | Q24: 0 | R24: 0 | S24: 0 | T24: 0 | U24: 0 | V24: 0 | W24: 0 | X24: 0
B25: Securities | C25: 0 | D25: 0 | E25: 0 | F25: 0 | G25: 0 | H25: 0 | I25: 0 | J25: 0 | K25: 0 | L25: 0 | M25: 0 | N25: 0 | O25: 49.673 | P25: 104.42 | Q25: 69.494 | R25: 481.242 | S25: 659.664 | T25: 885.418 | U25: 881.218 | V25: 1407.618 | W25: 2519.531 | X25: 3141.504
B26: Other receivables | C26: 0 | D26: 0 | E26: 0 | F26: 0 | G26: 0 | H26: 50.349 | I26: 285.632 | J26: 374.188 | K26: 381.782 | L26: 521.67 | M26: 1076.681 | N26: 1346.56 | O26: 1600.735 | P26: 1689.03 | Q26: 1405.969 | R26: 954.047 | S26: 971.286 | T26: 1413.443 | U26: 887.63 | V26: 929.533 | W26: 987.844 | X26: 1000.683
B27: Other financial assets | C27: 79.037 | D27: 22.87 | E27: 19.896 | F27: 24.899 | G27: 39.228 | H27: 18.493 | I27: 49.739 | J27: 61.136 | K27: 75.591 | L27: 478.283 | M27: 102.592 | N27: 141.099 | O27: 172.026 | P27: 131.519 | Q27: 167.666 | R27: 126.015 | S27: 180.827 | T27: 78.147 | U27: 107.371 | V27: 160.328 | W27: 231.796 | X27: 148.777
B28: Other assets | C28: 67.931 | D28: 123.495 | E28: 133.004 | F28: 176.253 | G28: 171.17 | H28: 232.915 | I28: 288.115 | J28: 331.383 | K28: 388.604 | L28: 541.903 | M28: 500.225 | N28: 706.514 | O28: 807.622 | P28: 936.209 | Q28: 567.552 | R28: 551.659 | S28: 667.126 | T28: 663.578 | U28: 1113.207 | V28: 1257.643 | W28: 1338.914 | X28: 1403.87
B29: Deferred tax assets | C29: 94.198 | D29: 125.131 | E29: 178.552 | F29: 266.89 | G29: 328.458 | H29: 360.752 | I29: 565.31 | J29: 598.917 | K29: 700.706 | L29: 811.05 | M29: 964.179 | N29: 1224.983 | O29: 1352.275 | P29: 1537.835 | Q29: 1710.214 | R29: 1700.803 | S29: 1898.399 | T29: 1818.339 | U29: 1832.587 | V29: 2055.502 | W29: 2233.675 | X29: 2510.967
B30: Investments in associates | C30: 0 | D30: 0 | E30: 0 | F30: 0 | G30: 0 | H30: 0 | I30: 0 | J30: 0 | K30: 0 | L30: 0 | M30: 0 | N30: 0 | O30: 0 | P30: 0 | Q30: 0 | R30: 0 | S30: 0 | T30: 99.365 | U30: 98.235 | V30: 97.21 | W30: 96.04 | X30: 98.702
B31: Right-of-use assets | C31: 17.195 | D31: 10.66 | E31: 8.977 | F31: 9.142 | G31: 7.454 | H31: 6.426 | I31: 18.994 | J31: 21.888 | K31: 17.301 | L31: 18.982 | M31: 16.811 | N31: 16.414 | O31: 26.027 | P31: 30.459 | Q31: 28.954 | R31: 24.972 | S31: 23.606 | T31: 20.344 | U31: 20.461 | V31: 20.754 | W31: 20.109 | X31: 22.244
B32: Property, plant and equipment | C32: 8.667 | D32: 9.85 | E32: 8.952 | F32: 12.69 | G32: 12.106 | H32: 14.109 | I32: 18.2 | J32: 18.658 | K32: 20.609 | L32: 27.482 | M32: 30.131 | N32: 35.246 | O32: 35.932 | P32: 39.294 | Q32: 36.53 | R32: 31.244 | S32: 29.873 | T32: 25.879 | U32: 25.62 | V32: 25.913 | W32: 25.642 | X32: 27.55
B33: Intangible assets | C33: 1.11 | D33: 12.372 | E33: 12.162 | F33: 59.24 | G33: 61.847 | H33: 72.337 | I33: 120.563 | J33: 147.432 | K33: 167.989 | L33: 182.164 | M33: 215.303 | N33: 254.378 | O33: 277.919 | P33: 295.881 | Q33: 307.399 | R33: 305.99 | S33: 357.64 | T33: 347.616 | U33: 439.835 | V33: 514.293 | W33: 574.972 | X33: 601.669
B34: Goodwill | C34: 0 | D34: 0.831 | E34: 0.831 | F34: 391.706 | G34: 393.82 | H34: 401.872 | I34: 409.573 | J34: 409.604 | K34: 397.334 | L34: 397.397 | M34: 397.486 | N34: 397.473 | O34: 397.505 | P34: 397.538 | Q34: 397.57 | R34: 397.602 | S34: 440.789 | T34: 414.287 | U34: 408.817 | V34: 410.347 | W34: 410.371 | X34: 409.371
B35: Total assets | C35: 6760.034 | D35: 10154.25 | E35: 10121.087 | F35: 13951.514 | G35: 14926.098 | H35: 19858.681 | I35: 24258.003 | J35: 25188.681 | K35: 26006.988 | L35: 29916.559 | M35: 29489.391 | N35: 33608.083 | O35: 35693.242 | P35: 43345.195 | Q35: 43839.497 | R35: 44802.73 | S35: 48637.85 | T35: 49931.214 | U35: 54192.525 | V35: 62730.144 | W35: 68362.816 | X35: 74893.877
B37: Liabilities
B38: Financial liabilities at fair value through profit or loss | C38: 24.125 | D38: 90.796 | E38: 75.279 | F38: 14.884 | G38: 99.169 | H38: 99.334 | I38: 197.305 | J38: 105.065 | K38: 23.147 | L38: 20.932 | M38: 13.276 | N38: 45.481 | O38: 56.491 | P38: 32.161 | Q38: 31.478 | R38: 19.821 | S38: 142.105 | T38: 32.329 | U38: 98.761 | V38: 124.501 | W38: 293.347 | X38: 65.969
B39: Derivatives | C39: 2.041 | D39: 75.304 | E39: 62.216 | F39: 0.122 | G39: 86.638 | H39: 87.278 | I39: 177.079 | J39: 86.511 | K39: 4.048 | L39: 9.425 | M39: 10.344 | N39: 41.715 | O39: 52.775 | P39: 28.173 | Q39: 27.488 | R39: 16.131 | S39: 142.105 | T39: 32.329 | U39: 98.761 | V39: 124.501 | W39: 293.347 | X39: 65.969
B40: Instruments eligible as capital | C40: 22.084 | D40: 15.492 | E40: 13.063 | F40: 14.762 | G40: 12.531 | H40: 12.056 | I40: 20.226 | J40: 18.554 | K40: 19.099 | L40: 11.507 | M40: 2.932 | N40: 3.766 | O40: 3.716 | P40: 3.988 | Q40: 3.99 | R40: 3.69 | S40: 0 | T40: 0 | U40: 0 | V40: 0 | W40: 0 | X40: 0
B41: Financial liabilities at amortized cost | C41: 5972.989 | D41: 9421.71 | E41: 8983.058 | F41: 11602.615 | G41: 12378.683 | H41: 14709.759 | I41: 18668.567 | J41: 19711.995 | K41: 20448.616 | L41: 23646.134 | M41: 23424.829 | N41: 26692.737 | O41: 28196.207 | P41: 34793.213 | Q41: 35859.702 | R41: 36481.096 | S41: 38856.565 | T41: 40227.546 | U41: 43872.763 | V41: 51140.501 | W41: 55234.258 | X41: 60741.103
B42: Deposits | C42: 2693.158 | D42: 5584.862 | E42: 5461.652 | F42: 7505.684 | G42: 8089.835 | H42: 9667.3 | I42: 12596.927 | J42: 13293.235 | K42: 14040.157 | L42: 15808.541 | M42: 15757.663 | N42: 18033.728 | O42: 19117.216 | P42: 23691.13 | Q42: 24254.885 | R42: 25228.578 | S42: 28319.121 | T42: 28855.065 | U42: 31564.365 | V42: 36640.156 | W42: 38775.929 | X42: 41925.101
B43: Payables to network | C43: 2976.505 | D43: 3331.258 | E43: 2982.547 | F43: 3990.411 | G43: 4127.691 | H43: 4882.159 | I43: 5920.795 | J43: 5930.966 | K43: 5894.436 | L43: 7054.783 | M43: 6871.826 | N43: 7749.565 | O43: 7834.854 | P43: 9755.285 | Q43: 9572.521 | R43: 8896.941 | S43: 8556.15 | T43: 9333.541 | U43: 10114.743 | V43: 11160.245 | W43: 11999.389 | X43: 13633.949
B44: Borrowings and financing | C44: 133.401 | D44: 97.454 | E44: 103.22 | F44: 59.165 | G44: 134.398 | H44: 147.243 | I44: 147.645 | J44: 470.881 | K44: 467.959 | L44: 585.568 | M44: 651.181 | N44: 764.522 | O44: 1085.87 | P44: 1136.344 | Q44: 1403.349 | R44: 1735.919 | S44: 1498.931 | T44: 1730.357 | U44: 1706.895 | V44: 2275.618 | W44: 3091.059 | X44: 4398.216
B45: Repurchase agreements | C45: 0 | D45: 0 | E45: 35.508 | F45: 0 | G45: 0 | H45: 3.046 | I45: 3.2 | J45: 16.913 | K45: 46.064 | L45: 197.242 | M45: 144.159 | N45: 144.922 | O45: 158.267 | P45: 210.454 | Q45: 628.947 | R45: 619.658 | S45: 482.363 | T45: 308.583 | U45: 486.76 | V45: 1064.482 | W45: 1367.881 | X45: 783.837
B46: Securitized borrowings | C46: 169.925 | D46: 79.742 | E46: 57.681 | F46: 47.355 | G46: 26.759 | H46: 10.011 | I46: 0 | J46: 0 | K46: 0 | L46: 0 | M46: 0 | N46: 0 | O46: 0 | P46: 0 | Q46: 0 | R46: 0 | S46: 0 | T46: 0 | U46: 0 | V46: 0 | W46: 0 | X46: 0
B47: Senior preferred shares | C47: 0 | D47: 328.394 | E47: 342.45 | F47: 0 | G47: 0 | H47: 0 | I47: 0 | J47: 0 | K47: 0 | L47: 0 | M47: 0 | N47: 0 | O47: 0 | P47: 0 | Q47: 0 | R47: 0 | S47: 0 | T47: 0 | U47: 0 | V47: 0 | W47: 0 | X47: 0
B48: Salaries, allowances and social security contributions | C48: 11.238 | D48: 25.848 | E48: 35.74 | F48: 53.995 | G48: 68.506 | H48: 97.909 | I48: 115.599 | J48: 88.07 | K48: 107.547 | L48: 90.587 | M48: 101.288 | N48: 150.033 | O48: 163.895 | P48: 166.876 | Q48: 191.544 | R48: 200.784 | S48: 222.529 | T48: 180.181 | U48: 180.441 | V48: 235.251 | W48: 242.655 | X48: 236.565
B49: Tax liabilities | C49: 12.43 | D49: 30.782 | E49: 40.162 | F49: 106.794 | G49: 166.326 | H49: 241.197 | I49: 140.797 | J49: 219.905 | K49: 323.375 | L49: 511.017 | M49: 259.223 | N49: 562.206 | O49: 848.679 | P49: 1300.845 | Q49: 320.379 | R49: 582.477 | S49: 948.536 | T49: 1102.086 | U49: 452.401 | V49: 718.015 | W49: 1089.679 | X49: 1424.118
... B55: Total liabilities | C55: 6147.783 | D55: 9716.139 | E55: 9317.24 | F55: 12014.419 | G55: 13020.695 | H55: 15416.14 | I55: 19467.421 | J55: 20450.522 | K55: 21254.306 | L55: 25025.776 | M55: 24280.87 | N55: 27963.484 | O55: 29803.924 | P55: 36938.81 | Q55: 37036.806 | R55: 37879.29 | S55: 40993.502 | T55: 42284.138 | U55: 45583.608 | V55: 53154.028 | W55: 57809.276 | X55: 63572.315
C56: 0 | D56: 0 | E56: 0 | F56: 0 | G56: 0 | H56: 0 | I56: 0 | J56: 0 | K56: 0 | L56: 0 | M56: 0 | N56: 0 | O56: 0 | P56: 0 | Q56: 0 | R56: 0 | S56: 0 | T56: 0 | U56: 0 | V56: 0 | W56: 0 | X56: 0
B57: Equity | C57: 0 | D57: 0 | E57: 0 | F57: 0 | G57: 0 | H57: 0 | I57: 0 | J57: 0 | K57: 0 | L57: 0 | M57: 0 | N57: 0 | O57: 0 | P57: 0 | Q57: 0 | R57: 0 | S57: 0 | T57: 0 | U57: 0 | V57: 0 | W57: 0 | X57: 0
B58: Share capital | C58: 0.045 | D58: 0.045 | E58: 0.048 | F58: 0.081 | G58: 0.081 | H58: 0.083 | I58: 0.083 | J58: 0.083 | K58: 0.083 | L58: 0.083 | M58: 0.083 | N58: 0.084 | O58: 0.084 | P58: 0.084 | Q58: 0.084 | R58: 0.084 | S58: 0.084 | T58: 0.084 | U58: 0.084 | V58: 0.084 | W58: 0.084 | X58: 0.084
B59: Share premium reserve | C59: 631.246 | D59: 638.007 | E59: 1038.361 | F59: 2112.245 | G59: 2113.501 | H59: 4678.585 | I59: 4960.557 | J59: 4962.573 | K59: 4963.187 | L59: 4963.774 | M59: 4965.793 | N59: 4970.786 | O59: 4971.814 | P59: 4972.922 | Q59: 4974.704 | R59: 4975.369 | S59: 5045.986 | T59: 5053.776 | U59: 5054.953 | V59: 5055.523 | W59: 5057.584 | X59: 5062.464
B60: Retained earnings | C60: 28.189 | D60: -102.441 | E60: -117.288 | F60: -104.818 | G60: -108.893 | H60: -128.409 | I60: -116.805 | J60: -95.911 | K60: -45.876 | L60: 64.577 | M60: 257.09 | N60: 546.742 | O60: 887.813 | P60: 1276.949 | Q60: 1716.077 | R60: 2254.763 | S60: 2847.553 | T60: 3420.596 | U60: 4033.513 | V60: 4692.246 | W60: 5491.155 | X60: 6412.7
B61: Other comprehensive income (loss) | C61: -47.229 | D61: -97.5 | E61: -117.274 | F61: -70.413 | G61: -101.016 | H61: -109.227 | I61: -54.79 | J61: -128.586 | K61: -164.712 | L61: -137.651 | M61: -14.445 | N61: 126.987 | O61: 29.607 | P61: 156.43 | Q61: 111.826 | R61: -306.776 | S61: -249.275 | T61: -828.167 | U61: -480.641 | V61: -173.018 | W61: 3.168 | X61: -184.3
B62: Equity attributable to shareholders of the parent company | C62: 612.251 | D62: 438.111 | E62: 803.847 | F62: 1937.095 | G62: 1903.673 | H62: 4441.032 | I62: 4789.045 | J62: 4738.159 | K62: 4752.682 | L62: 4890.783 | M62: 5208.521 | N62: 5644.599 | O62: 5889.318 | P62: 6406.385 | Q62: 6802.691 | R62: 6923.44 | S62: 7644.348 | T62: 7646.289 | U62: 8607.909 | V62: 9574.835 | W62: 10551.991 | X62: 11290.948
B63: Equity attributable to non-controlling interests | C63: 0 | D63: 0 | E63: 0 | F63: 0 | G63: 1.73 | H63: 1.509 | I63: 1.537 | J63: 0 | K63: 0 | L63: 0 | M63: 0 | N63: 0 | O63: 0 | P63: 0 | Q63: 0 | R63: 0 | S63: 0 | T63: 0.787 | U63: 1.008 | V63: 1.281 | W63: 1.549 | X63: 30.614
B64: Total equity | C64: 612.251 | D64: 438.111 | E64: 803.847 | F64: 1937.095 | G64: 1905.403 | H64: 4442.541 | I64: 4790.582 | J64: 4738.159 | K64: 4752.682 | L64: 4890.783 | M64: 5208.521 | N64: 5644.599 | O64: 5889.318 | P64: 6406.385 | Q64: 6802.691 | R64: 6923.44 | S64: 7644.348 | T64: 7647.076 | U64: 8608.917 | V64: 9576.116 | W64: 10553.54 | X64: 11321.562
C65: 0 | D65: 0 | E65: 0 | F65: 0 | G65: 0 | H65: 0 | I65: 0 | J65: 0 | K65: 0 | L65: 0 | M65: 0 | N65: 0 | O65: 0 | P65: 0 | Q65: 0 | R65: 0 | S65: 0 | T65: 0 | U65: 0 | V65: 0 | W65: 0 | X65: 0
B66: Total liabilities and equity | C66: 6760.034 | D66: 10154.25 | E66: 10121.087 | F66: 13951.514 | G66: 14926.098 | H66: 19858.681 | I66: 24258.003 | J66: 25188.681 | K66: 26006.988 | L66: 29916.559 | M66: 29489.391 | N66: 33608.083 | O66: 35693.242 | P66: 43345.195 | Q66: 43839.497 | R66: 44802.73 | S66: 48637.85 | T66: 49931.214 | U66: 54192.525 | V66: 62730.144 | W66: 68362.816 | X66: 74893.877

Sheet IFRS - Cash Flow
B2: Nu Holdings Ltd.
B3: Consolidated Statement of Cash Flow
B4: Amounts in million of US$
B5: Back to Contents
C9: 43830 | D9: 43921 | E9: 44012 | F9: 44104 | G9: 44196 | H9: 44286 | I9: 44377 | J9: 44469 | K9: 44561 | L9: 44651 | M9: 44742 | N9: 44834 | O9: 44926 | P9: 45016 | Q9: 45107 | R9: 45199 | S9: 45291 | T9: 45382 | U9: 45473 | V9: 45565 | W9: 45657 | X9: 45747 | Y9: 45838 | Z9: 45930 | AA9: 46022
C10: US$ | D10: US$ | E10: US$ | F10: US$ | G10: US$ | H10: US$ | I10: US$ | J10: US$ | K10: US$ | L10: US$ | M10: US$ | N10: US$ | O10: US$ | P10: US$ | Q10: US$ | R10: US$ | S10: US$ | T10: US$ | U10: US$ | V10: US$ | W10: US$ | X10: US$ | Y10: US$ | Z10: US$ | AA10: US$
B11: Cash flows from operating activities
B12: Reconciliation of profit (loss) to net cash flows from operating activities:
B13: Profit (Loss) for the period/year | C13: -92.531 | D13: -33.433 | E13: -31.872 | F13: -64.434 | G13: -171.491 | H13: -49.483 | I13: -64.703 | J13: -99.06 | K13: -165.334 | L13: -45.004 | M13: -74.854 | N13: -67.021 | O13: -364.634 | P13: 141.751 | Q13: 366.617 | R13: 669.653 | S13: 1030.53 | T13: 378.814 | U13: 866.086 | V13: 1419.472 | W13: 1972.112 | X13: 557.208 | Y13: 1194.195 | Z13: 1976.873 | AA13: 2871.672
B14: Adjustments:
B15: Depreciation and amortization | C15: 5.073 | D15: 0.56 | E15: 2.893 | F15: 3.783 | G15: 7.428 | H15: 2.507 | I15: 5.242 | J15: 10.896 | K15: 17.339 | L15: 7.655 | M15: 18.088 | N15: 25.699 | O15: 35.581 | P15: 13.179 | Q15: 27.156 | R15: 46.35 | S15: 62.895 | T15: 18.465 | U15: 36.798 | V15: 56.067 | W15: 77.128 | X15: 21.322 | Y15: 44.392 | Z15: 69.962 | AA15: 97.968
B16: Expected credit loss | C16: 193.967 | D16: 64.181 | E16: 87.43 | F16: 126.184 | G16: 187.79 | H16: 77.21 | I16: 165.815 | J16: 299.404 | K16: 503.679 | L16: 279.489 | M16: 625.185 | N16: 1009.827 | O16: 1440.922 | P16: 491.937 | Q16: 1106.8 | R16: 1784.854 | S16: 2487.648 | T16: 883.498 | U16: 1718.49 | V16: 2569.667 | W16: 3469.044 | X16: 1074.571 | Y16: 2189.754 | Z16: 3304.609 | AA16: 4701.058
B17: Deferred income taxes | C17: -40.34 | D17: -19.404 | E17: -18.613 | F17: -24.079 | G17: -44.025 | H17: -35.392 | I17: -78.958 | J17: -132.732 | K17: -224.654 | L17: -121.699 | M17: -212.71 | N17: -322.255 | O17: -417.612 | P17: -103.986 | Q17: -267.946 | R17: -466.685 | S17: -675.682 | T17: -215.319 | U17: -401.179 | V17: -566.243 | W17: -713.435 | X17: 156.751 | Y17: -40.329 | Z17: -95.425 | AA17: -427.259
B18: Customer program | C18: 0 | D18: 0 | E18: 0 | F18: 0 | G18: 0 | H18: 0 | I18: 0 | J18: 0 | K18: 11.18 | L18: 0 | M18: 0 | N18: 0 | O18: 0 | P18: 0 | Q18: 0 | R18: 0 | S18: 0 | T18: 0 | U18: 0 | V18: 0 | W18: 0 | X18: 0 | Y18: 0 | Z18: 0 | AA18: 0
B19: Provisions and contingent liabilities | C19: 7.386 | D19: 0.131 | E19: 0.154 | F19: 0.338 | G19: 0.227 | H19: 0.338 | I19: 0.32 | J19: 0.502 | K19: 2.818 | L19: -2.147 | M19: -1.958 | N19: -1.382 | O19: -1.174 | P19: 1.239 | Q19: 2.502 | R19: 3.47 | S19: 17.098 | T19: 5.823 | U19: 10.234 | V19: 15.079 | W19: 18.406 | X19: 0.96 | Y19: 2.122 | Z19: 20.264 | AA19: 29.238
B20: Unrealized (gains) losses on financial instruments | C20: 1.799 | D20: -6.524 | E20: -18.584 | F20: 13.067 | G20: 48.433 | H20: 87.09 | I20: 95.216 | J20: 161.37 | K20: 19.338 | L20: 13.508 | M20: 38.458 | N20: 14.063 | O20: 17.794 | P20: 4.437 | Q20: 51.705 | R20: 42.995 | S20: 15.885 | T20: -1.074 | U20: -26.457 | V20: -65.315 | W20: 47.933 | X20: -16.314 | Y20: 56.662 | Z20: -68.824 | AA20: -50.432
B21: Interest accrued | C21: 17.681 | D21: 4.353 | E21: 7.185 | F21: 22.77 | G21: 39.521 | H21: 16.946 | I21: 4.658 | J21: 7.186 | K21: 11.077 | L21: 3.706 | M21: 8.907 | N21: 21.877 | O21: 32.479 | P21: 16.463 | Q21: 40.139 | R21: 68.843 | S21: 103.572 | T21: 41.326 | U21: 72.938 | V21: 147.924 | W21: 179.203 | X21: 47.623 | Y21: 106.059 | Z21: 188.185 | AA21: 288.682
B22: Share-based payments - Contingency share award (CSA) - termination | C22: 0 | D22: 0 | E22: 0 | F22: 0 | G22: 0 | H22: 0 | I22: 0 | J22: 0 | K22: 0 | L22: 0 | M22: 0 | N22: 0 | O22: 355.573 | P22: 0 | Q22: 0 | R22: 0 | S22: 0 | T22: 0 | U22: 0 | V22: 0 | W22: 0 | X22: 0 | Y22: 0 | Z22: 0 | AA22: 0
B23: Share-based compensation | C23: 18.511 | D23: 7.111 | E23: 14.053 | F23: 20.157 | G23: 35.569 | H23: 32.2 | I23: 53.512 | J23: 79.729 | K23: 152.717 | L23: 42.1 | M23: 135.656 | N23: 188.525 | O23: 253.203 | P23: 57.857 | Q23: 116.85 | R23: 168.97 | S23: 212.551 | T23: 78.649 | U23: 158.848 | V23: 224.766 | W23: 272.382 | X23: 77.785 | Y23: 134.836 | Z23: 208.571 | AA23: 271.845
B24: Unrealized losses on other investments | C24: 0 | D24: 0 | E24: 0 | F24: 0 | G24: 0 | H24: 0 | I24: 0 | J24: 0 | K24: -39.28 | L24: -14.055 | M24: -5.067 | N24: -5.067 | O24: 0.848 | P24: 18.298 | Q24: 21.72 | R24: 21.72 | S24: 0.02 | T24: 0 | U24: 0 | V24: 0 | W24: -0.011 | X24: 0 | Y24: 0 | Z24: 0 | AA24: 0
B25: Income of share of profit or (loss) in associates | C25: 0 | D25: 0 | E25: 0 | F25: 0 | G25: 0 | H25: 0 | I25: 0 | J25: 0 | K25: 0 | L25: 0 | M25: 0 | N25: 0 | O25: 0 | P25: 0 | Q25: 0 | R25: 0 | S25: 0 | T25: 0 | U25: 0 | V25: 0 | W25: 0 | X25: 1.13 | Y25: 2.155 | Z25: 3.325 | AA25: 3.689
B26: Others | C26: 0 | D26: 0 | E26: 0 | F26: 0 | G26: 0 | H26: 0 | I26: 0 | J26: 0 | K26: 0 | L26: 0 | M26: 0 | N26: 5.879 | O26: 8.203 | P26: 0 | Q26: 0 | R26: 14.025 | S26: 23.056 | T26: 2.088 | U26: 2.327 | V26: 5.69 | W26: -2.712 | X26: -2.121 | Y26: 13.492 | Z26: 37.718 | AA26: 86.676
C27: 111.546 | D27: 16.975 | E27: 42.646 | F27: 97.786 | G27: 103.452 | H27: 131.416 | I27: 181.102 | J27: 327.295 | K27: 288.88 | L27: 163.553 | M27: 531.705 | N27: 870.145 | O27: 1361.183 | P27: 641.175 | Q27: 1465.543 | R27: 2354.195 | S27: 3277.573 | T27: 1192.27 | U27: 2438.085 | V27: 3807.107 | W27: 5320.05 | X27: 1918.915 | Y27: 3703.338 | Z27: 5645.258 | AA27: 7873.137
B28: Changes in operating assets and liabilities:
B29: Securities | C29: -1689.547 | D29: 102.672 | E29: -178.688 | F29: -865.895 | G29: -2008.861 | H29: -1089.592 | I29: -1238.495 | J29: -2279.875 | K29: -4666.792 | L29: -991.777 | M29: -773.539 | N29: -749.991 | O29: -1102.864 | P29: 1968.358 | Q29: 2221.786 | R29: 1279.337 | S29: 699.076 | T29: -218.559 | U29: -165.656 | V29: -2626.719 | W29: -2552.241 | X29: 335.731 | Y29: -1030.858 | Z29: -3643.301 | AA29: -4812.896
B30: Credit card receivables | C30: -1414.489 | D30: 345.824 | E30: 366.816 | F30: 652.567 | G30: -470.227 | H30: -608.551 | I30: -1066.399 | J30: -1594.432 | K30: -2568.423 | L30: -1576.633 | M30: -2459.157 | N30: -3502.428 | O30: -5213.669 | P30: -1577.046 | Q30: -3246.823 | R30: -5060.879 | S30: -7878.307 | T30: -1740.047 | U30: -2444.542 | V30: -2800.856 | W30: -5873.063 | X30: -2750.317 | Y30: -5562.22 | Z30: -8605.99 | AA30: -12445.835
B31: Loans to customers | C31: -63.009 | D31: -24.499 | E31: -18.514 | F31: -27.279 | G31: -178.686 | H31: -175.395 | I31: -426.329 | J31: -875.629 | K31: -1522.217 | L31: -673.86 | M31: -1145.997 | N31: -1548.747 | O31: -1889.278 | P31: -702.67 | Q31: -1245.332 | R31: -2453.595 | S31: -3577.534 | T31: -1564.023 | U31: -2899.339 | V31: -3529.963 | W31: -7024.003 | X31: -2790.768 | Y31: -5072.2 | Z31: -7706.23 | AA31: -10306.93
B32: Other receivables | C32: 0 | D32: 0 | E32: 0 | F32: 0 | G32: 0 | H32: 0 | I32: 0 | J32: 0 | K32: 0 | L32: 0 | M32: -335.367 | N32: -349.558 | O32: -481.824 | P32: -541.19 | Q32: -778.678 | R32: -1086.236 | S32: -1136.488 | T32: 286.98 | U32: 809.346 | V32: 746.405 | W32: 385.192 | X32: 512.972 | Y32: 456.906 | Z32: 401.17 | AA32: 406.251
B33: Compulsory deposits and others at central banks | C33: 0 | D33: 0 | E33: 0 | F33: 0 | G33: -43.841 | H33: -65.951 | I33: -204.739 | J33: -386.869 | K33: -924.889 | L33: -358.253 | M33: -635.319 | N33: -972.188 | O33: -1880.347 | P33: 103.703 | Q33: -46.123 | R33: -3087.936 | S33: -4540.463 | T33: 447.155 | U33: 859.724 | V33: 672.489 | W33: 805.963 | X33: -616.755 | Y33: -1384.32 | Z33: -1340.493 | AA33: -2749.819
B34: Interbank transactions | C34: -0.091 | D34: 0.093 | E34: -3.142 | F34: -5.008 | G34: 0.093 | H34: -1.462 | I34: -4.106 | J34: -20.153 | K34: 0 | L34: 0 | M34: 0 | N34: 0 | O34: 0 | P34: 0 | Q34: 0 | R34: 0 | S34: 0 | T34: 0 | U34: 0 | V34: 0 | W34: 0 | X34: 0 | Y34: 0 | Z34: 0 | AA34: 0
B35: Other assets | C35: -166.173 | D35: -17.671 | E35: 84.742 | F35: 77.888 | G35: 78.319 | H35: -14.617 | I35: -1.353 | J35: 19.379 | K35: -64.072 | L35: -299.995 | M35: -145.172 | N35: -210.427 | O35: -772.415 | P35: 406.972 | Q35: 163.262 | R35: 33.994 | S35: -60.982 | T35: 334.622 | U35: 426.486 | V35: 223.682 | W35: 369.19 | X35: -467.161 | Y35: -638.178 | Z35: -780.969 | AA35: -828.6
B36: Deposits | C36: 2088.793 | D36: 12.212 | E36: 773.253 | F36: 1529.163 | G36: 2871.246 | H36: 1067.551 | I36: 1579.763 | J36: 2343.522 | K36: 4001.856 | L36: 2658.644 | M36: 3755.012 | N36: 4611.994 | O36: 6278.088 | P36: -49.611 | Q36: 2100.527 | R36: 3326.45 | S36: 7664.82 | T36: 570.928 | U36: 1691.175 | V36: 4808.325 | W36: 5910.612 | X36: 2643.104 | Y36: 7346.845 | Z36: 9347.544 | AA36: 12861.282
B37: Payables to network | C37: 1365.476 | D37: -485.189 | E37: -601.255 | F37: -510.635 | G37: 312.607 | H37: 354.124 | I37: 608.114 | J37: 812.739 | K37: 1602.485 | L37: 942.565 | M37: 1086.143 | N37: 1067.635 | O37: 2221.037 | P37: -178.401 | Q37: 655.859 | R37: 943.798 | S37: 2818.592 | T37: -156.255 | U37: -951.82 | V37: -1266.302 | W37: -528.511 | X37: 734.894 | Y37: 1672.174 | Z37: 2436.827 | AA37: 4132.411
B38: Deferred income | C38: 10.325 | D38: 0.063 | E38: 1.69 | F38: -3.095 | G38: 3.621 | H38: 5.869 | I38: 5.216 | J38: 3.525 | K38: 4.848 | L38: 5.884 | M38: 6.149 | N38: 6.11 | O38: 11.277 | P38: 5.299 | Q38: 12.455 | R38: 19.649 | S38: 25.935 | T38: -0.866 | U38: -6.231 | V38: 3.105 | W38: 3.75 | X38: 13.483 | Y38: 32.712 | Z38: 36.215 | AA38: 5.791
B39: Other liabilities | C39: 52.366 | D39: 0.364 | E39: -1.997 | F39: 32.278 | G39: 57.841 | H39: 111.629 | I39: 128.811 | J39: 278.819 | K39: 417.225 | L39: 144.112 | M39: 230.43 | N39: 423.586 | O39: 979.277 | P39: -134.691 | Q39: 197.455 | R39: 632.384 | S39: 1279.987 | T39: -2.543 | U39: 716.369 | V39: 701.421 | W39: 1111.83 | X39: 878.488 | Y39: 1741.209 | Z39: 2490.96 | AA39: 2659.676
B40: Interest paid | C40: -15.603 | D40: -2.112 | E40: -3.524 | F40: -4.253 | G40: -6.199 | H40: -1.189 | I40: -6.707 | J40: -7.95 | K40: -9.062 | L40: -5.3 | M40: -8.274 | N40: -20.295 | O40: -30.935 | P40: -18.832 | Q40: -36.152 | R40: -64.962 | S40: -82.904 | T40: -36.26 | U40: -56.364 | V40: -87.84 | W40: -88.082 | X40: -20.36 | Y40: -29.312 | Z40: -82.634 | AA40: -92.292
... B43: Cash flows (used in) generated from operating activities | C43: 276.136 | D43: -56.655 | E43: 604.056 | F43: 1168.811 | G43: 974.52 | H43: -222.744 | I43: -273.457 | J43: -1065.191 | K43: -2928.925 | L43: 78.302 | M43: 542.632 | N43: 527.22 | O43: 755.573 | P43: 94.292 | Q43: 1794.059 | R43: -1440.302 | S43: 1266.189 | T43: -570.619 | U43: 2097.809 | V43: 1028.947 | W43: 2399.044 | X43: 1085.345 | Y43: 3640.032 | Z43: 2669.433 | AA43: 3500.464
B45: Cash flows from investing activities
B46: Acquisition of property, plant and equipment | C46: -2.377 | D46: -0.245 | E46: -1.522 | F46: -1.738 | G46: -3.084 | H46: -1.779 | I46: -2.01 | J46: -2.544 | K46: -6.025 | L46: -4.683 | M46: -7.425 | N46: -11.396 | O46: -20.001 | P46: -4.596 | Q46: -11.403 | R46: -15.453 | S46: -20.243 | T46: -0.21 | U46: 3.401 | V46: 2.307 | W46: -5.418 | X46: -2.4 | Y46: -4.394 | Z46: -6.949 | AA46: -7.215
B47: Acquisition and development of intangible assets | C47: -2.302 | D47: 0 | E47: -1.322 | F47: -3.385 | G47: -4.902 | H47: -3.424 | I47: -3.492 | J47: -12.579 | K47: -22.473 | L47: -10.059 | M47: -45.611 | N47: -75.22 | O47: -94.305 | P47: -41.919 | Q47: -87.257 | R47: -130.683 | S47: -156.76 | T47: -26.573 | U47: -43.611 | V47: -79.377 | W47: -169.572 | X47: -80.115 | Y47: -148.499 | Z47: -271.213 | AA47: -333.554
B48: Investment in associates | C48: 0 | D48: 0 | E48: 0 | F48: 0 | G48: 0 | H48: 0 | I48: 0 | J48: 0 | K48: 0 | L48: 0 | M48: 0 | N48: 0 | O48: 0 | P48: 0 | Q48: 0 | R48: 0 | S48: 0 | T48: 0 | U48: 0 | V48: 0 | W48: -99.365 | X48: 1.13 | Y48: 0 | Z48: 0 | AA48: 0
B49: Acquisition of subsidiary, net of cash acquired | C49: 0 | D49: 0 | E49: 0 | F49: -8.283 | G49: -8.284 | H49: 0 | I49: -108.993 | J49: -108.993 | K49: -114.486 | L49: -10.346 | M49: -10.346 | N49: -10.346 | O49: -10.346 | P49: 0 | Q49: 0 | R49: 0 | S49: 0 | T49: 0 | U49: 0 | V49: -5.637 | W49: -5.637 | X49: 0 | Y49: 0 | Z49: 0 | AA49: -1.539
B50: Financial instruments derivatives | C50: 0 | D50: 0 | E50: 0 | F50: 0 | G50: 0 | H50: 0 | I50: 0 | J50: 0 | K50: 0 | L50: 0 | M50: 0 | N50: 0 | O50: 0 | P50: 0 | Q50: 0 | R50: 0 | S50: 0 | T50: 0 | U50: 0 | V50: 0 | W50: -50.635 | X50: 0 | Y50: 0 | Z50: 0 | AA50: 0
B51: Acquisition of securities - equity instruments | C51: 0 | D51: 0 | E51: 0 | F51: 0 | G51: 0 | H51: 0 | I51: 0 | J51: 0 | K51: -11.211 | L51: -13.131 | M51: -2.5 | N51: -2.5 | O51: -2.5 | P51: 0 | Q51: 0 | R51: 0 | S51: 0 | T51: 0 | U51: 0 | V51: 0 | W51: 0 | X51: 0 | Y51: 0 | Z51: 0 | AA51: 0
B52: Cash flow (used in) generated from investing activities | C52: -4.679 | D52: -0.245 | E52: -2.844 | F52: -13.406 | G52: -16.27 | H52: -5.203 | I52: -114.495 | J52: -124.116 | K52: -154.195 | L52: -38.219 | M52: -65.882 | N52: -99.462 | O52: -127.152 | P52: -46.515 | Q52: -98.66 | R52: -146.136 | S52: -177.003 | T52: -26.783 | U52: -40.21 | V52: -82.707 | W52: -330.627 | X52: -81.385 | Y52: -152.893 | Z52: -278.162 | AA52: -342.308
B54: Cash flows from financing activities
B55: Proceeds from senior preferred shares | C55: 0 | D55: 0 | E55: 300 | F55: 300 | G55: 300 | H55: 0 | I55: 0 | J55: 0 | K55: 0 | L55: 0 | M55: 0 | N55: 0 | O55: 0 | P55: 0 | Q55: 0 | R55: 0 | S55: 0 | T55: 0 | U55: 0 | V55: 0 | W55: 0 | X55: 0 | Y55: 0 | Z55: 0 | AA55: 0
B56: Issuance of preferred shares | C56: 400.001 | D56: 0 | E56: 0 | F56: 0 | G56: 0 | H56: 400 | I56: 800 | J56: 800 | K56: 800 | L56: 0 | M56: 0 | N56: 0 | O56: 0 | P56: 0 | Q56: 0 | R56: 0 | S56: 0 | T56: 0 | U56: 0 | V56: 0 | W56: 0 | X56: 0 | Y56: 0 | Z56: 0 | AA56: 0
B57: Issuance of shares under IPO | C57: 0 | D57: 0 | E57: 0 | F57: 0 | G57: 0 | H57: 0 | I57: 0 | J57: 0 | K57: 2590.846 | L57: 0 | M57: 0 | N57: 0 | O57: 0 | P57: 0 | Q57: 0 | R57: 0 | S57: 0 | T57: 0 | U57: 0 | V57: 0 | W57: 0 | X57: 0 | Y57: 0 | Z57: 0 | AA57: 0
B58: Transactions costs from IPO | C58: 0 | D58: 0 | E58: 0 | F58: 0 | G58: 0 | H58: 0 | I58: 0 | J58: 0 | K58: -47.545 | L58: 0 | M58: 0 | N58: 0 | O58: 0 | P58: 0 | Q58: 0 | R58: 0 | S58: 0 | T58: 0 | U58: 0 | V58: 0 | W58: 0 | X58: 0 | Y58: 0 | Z58: 0 | AA58: 0
B59: Issuance of shares for over-allotment in IPO | C59: 0 | D59: 0 | E59: 0 | F59: 0 | G59: 0 | H59: 0 | I59: 0 | J59: 0 | K59: 0 | L59: 247.998 | M59: 247.998 | N59: 247.998 | O59: 247.998 | P59: 0 | Q59: 0 | R59: 0 | S59: 0 | T59: 0 | U59: 0 | V59: 0 | W59: 0 | X59: 0 | Y59: 0 | Z59: 0 | AA59: 0
B60: Transactions costs for over-allotment in IPO | C60: 0 | D60: 0 | E60: 0 | F60: 0 | G60: 0 | H60: 0 | I60: 0 | J60: 0 | K60: 0 | L60: -3.985 | M60: -3.985 | N60: -3.985 | O60: -3.985 | P60: 0 | Q60: 0 | R60: 0 | S60: 0 | T60: 0 | U60: 0 | V60: 0 | W60: 0 | X60: 0 | Y60: 0 | Z60: 0 | AA60: 0
B61: Proceeds from securitized borrowings | C61: 126.768 | D61: 0 | E61: 0 | F61: 0 | G61: 0 | H61: 0 | I61: 0 | J61: 0 | K61: 0 | L61: 0 | M61: 0 | N61: 0 | O61: 0 | P61: 0 | Q61: 0 | R61: 0 | S61: 0 | T61: 0 | U61: 0 | V61: 0 | W61: 0 | X61: 0 | Y61: 0 | Z61: 0 | AA61: 0
B62: Payments of securitized borrowings | C62: -16.835 | D62: -8.85 | E62: -16.058 | F62: -28.797 | G62: -52.172 | H62: -15.873 | I62: -33.261 | J62: -50.387 | K62: -66.403 | L62: -10.633 | M62: -10.633 | N62: -10.633 | O62: -10.633 | P62: 0 | Q62: 0 | R62: 0 | S62: 0 | T62: 0 | U62: 0 | V62: 0 | W62: 0 | X62: 0 | Y62: 0 | Z62: 0 | AA62: 0
B63: Proceeds from borrowings and financing | C63: 160.577 | D63: 0 | E63: 0 | F63: 0 | G63: 17.974 | H63: 16.568 | I63: 26.955 | J63: 106.393 | K63: 116.349 | L63: 0 | M63: 353.878 | N63: 353.093 | O63: 581.142 | P63: 19.713 | Q63: 95.419 | R63: 459.154 | S63: 469.501 | T63: 269.726 | U63: 813.014 | V63: 988.295 | W63: 1309.89 | X63: 187.171 | Y63: 636.307 | Z63: 1533.63 | AA63: 2823.472
B64: Payments of borrowings and financing | C64: -78.185 | D64: -4.484 | E64: -5.583 | F64: -8.697 | G64: -27.893 | H64: -4.729 | I64: -60.244 | J64: -61.234 | K64: -60.523 | L64: -7.767 | M64: -38.305 | N64: -38.208 | O64: -159.983 | P64: 0 | Q64: -10.546 | R64: -46.339 | S64: -46.501 | T64: -11.465 | U64: -93.964 | V64: -580.642 | W64: -580.642 | X64: -355.041 | Y64: -368.942 | Z64: -524.213 | AA64: -532.755
B65: Proceeds from debt instruments eligible as capital | C65: 18.824 | D65: 0 | E65: 0 | F65: 0 | G65: 0 | H65: 0 | I65: 0 | J65: 0 | K65: 0 | L65: 0 | M65: 0 | N65: 0 | O65: 0 | P65: 0 | Q65: 0 | R65: 0 | S65: 0 | T65: 0 | U65: 0 | V65: 0 | W65: 0 | X65: 0 | Y65: 0 | Z65: 0 | AA65: 0
B66: Lease payments | C66: -2.014 | D66: -1.311 | E66: -2.385 | F66: -3.394 | G66: -4.568 | H66: -1.08 | I66: -2.197 | J66: -3.326 | K66: -4.387 | L66: -1.255 | M66: -2.416 | N66: -3.394 | O66: -5.005 | P66: -1.858 | Q66: -3.803 | R66: -5.535 | S66: -6.933 | T66: -1.823 | U66: -3.567 | V66: -5.209 | W66: -7.053 | X66: -1.728 | Y66: -3.05 | Z66: -5.205 | AA66: -6.708
... B71: Change in cash and cash equivalents | C71: 882.651 | D71: -71.018 | E71: 878.631 | F71: 1417.266 | G71: 1198.352 | H71: 167.296 | I71: 349.88 | J71: -394.475 | K71: 257.469 | L71: 265.729 | M71: 1026.591 | N71: 976.547 | O71: 1282.46 | P71: 67.651 | Q71: 1783.482 | R71: -1171.117 | S71: 1514.401 | T71: -339.182 | U71: 2775.529 | V71: 1352.532 | W71: 2796.158 | X71: 834.76 | Y71: 3752.422 | Z71: 3397.708 | AA71: 5448.386
B73: Cash and cash equivalents
B74: Cash and cash equivalents - beginning of the period/year | C74: 379.207 | D74: 1246.566 | E74: 1246.566 | F74: 1246.566 | G74: 1246.566 | H74: 2343.78 | I74: 2343.78 | J74: 2343.78 | K74: 2343.78 | L74: 2705.675 | M74: 2705.675 | N74: 2705.675 | O74: 2705.675 | P74: 4172.316 | Q74: 4172.316 | R74: 4172.316 | S74: 4172.316 | T74: 5923.44 | U74: 5923.44 | V74: 5923.44 | W74: 5923.44 | X74: 9185.742 | Y74: 9185.742 | Z74: 9185.742 | AA74: 9185.742
B75: Foreign exchange rate changes on cash and cash equivalents | C75: -15.292 | D75: -143.046 | E75: -217.779 | F75: -606.598 | G75: -101.138 | H75: -310.413 | I75: -31.193 | J75: 47.42 | K75: 104.426 | L75: -2.782 | M75: -31.246 | N75: 10.571 | O75: 184.181 | P75: 70.529 | Q75: 219.251 | R75: 212.428 | S75: 236.723 | T75: 449.4 | U75: -168.586 | V75: 369.782 | W75: 466.144 | X75: 263.505 | Y75: 330.853 | Z75: 312.335 | AA75: 369.515
B76: Cash and cash equivalents - end of the period/year | C76: 1246.566 | D76: 1032.502 | E76: 1907.418 | F76: 2057.234 | G76: 2343.78 | H76: 2200.663 | I76: 2662.467 | J76: 1996.725 | K76: 2705.675 | L76: 2968.622 | M76: 3701.02 | N76: 3692.793 | O76: 4172.316 | P76: 4310.496 | Q76: 6175.049 | R76: 3213.627 | S76: 5923.44 | T76: 6033.658 | U76: 8530.383 | V76: 7645.754 | W76: 9185.742 | X76: 10284.007 | Y76: 13269.017 | Z76: 12895.785 | AA76: 15003.643
C77: 0 | D77: 0 | E77: 0 | F77: 0 | G77: 0 | H77: 0 | I77: 0 | J77: 0 | K77: 0 | L77: 0 | M77: 0 | N77: 0 | O77: 0 | P77: 0 | Q77: 0 | R77: 0 | S77: 0 | T77: 0 | U77: 0 | V77: 0 | W77: 0 | X77: 0 | Y77: 0 | Z77: 0 | AA77: 0
B78: Increase (decrease) in cash and cash equivalents | C78: 882.651 | D78: -71.018 | E78: 878.631 | F78: 1417.266 | G78: 1198.352 | H78: 167.296 | I78: 349.88 | J78: -394.475 | K78: 257.469 | L78: 265.729 | M78: 1026.591 | N78: 976.547 | O78: 1282.46 | P78: 67.651 | Q78: 1783.482 | R78: -1171.117 | S78: 1514.401 | T78: -339.182 | U78: 2775.529 | V78: 1352.532 | W78: 2796.158 | X78: 834.76 | Y78: 3752.422 | Z78: 3397.708 | AA78: 5448.386
B81: The information included in this spreadsheet is acumulated as of date.

Sheet IFRS - Revenue breakdown 
B2: Nu Holdings Ltd.
B3: Revenue Breakdown
B4: Amounts in million of US$
B5: Back to Contents
C8: 3-MONTH PERIOD ENDED
C9: 43921 | D9: 44012 | E9: 44104 | F9: 44196 | G9: 44286 | H9: 44377 | I9: 44469 | J9: 44561 | K9: 44651 | L9: 44742 | M9: 44834 | N9: 44926 | O9: 45016 | P9: 45107 | Q9: 45199 | R9: 45291 | S9: 45382 | T9: 45473 | U9: 45565 | V9: 45657 | W9: 45747 | X9: 45838 | Y9: 45930 | Z9: 46022
C10: US$ | D10: US$ | E10: US$ | F10: US$ | G10: US$ | H10: US$ | I10: US$ | J10: US$ | K10: US$ | L10: US$ | M10: US$ | N10: US$ | O10: US$ | P10: US$ | Q10: US$ | R10: US$ | S10: US$ | T10: US$ | U10: US$ | V10: US$ | W10: US$ | X10: US$ | Y10: US$ | Z10: US$
B11: Interest income – credit card | C11: 69.4 | D11: 58.533 | E11: 41.569 | F11: 48.003 | G11: 61.442 | H11: 83.075 | I11: 94.054 | J11: 119.26 | K11: 189.52 | L11: 243.916 | M11: 262.207 | N11: 319.232 | O11: 447.696 | P11: 593.855 | Q11: 679.746 | R11: 800.595 | S11: 983.573 | T11: 985.139 | U11: 966.663 | V11: 866.991 | W11: 951.569 | X11: 1091.598 | Y11: 1219.239 | Z11: 1335.364
B12: Interest income – loan | C12: 7.563 | D12: 6.234 | E12: 8.406 | F12: 16.723 | G12: 29.52 | H12: 47.125 | I12: 84.579 | J12: 131.477 | K12: 194.147 | L12: 228.035 | M12: 250.443 | N12: 259.571 | O12: 286.943 | P12: 353.082 | Q12: 453.415 | R12: 556.881 | S12: 655.961 | T12: 730.002 | U12: 787.051 | V12: 865.649 | W12: 1007.239 | X12: 1128.02 | Y12: 1252.363 | Z12: 1396.641
B13: Interest income – other assets at amortized cost | C13: 9.082 | D13: 9.254 | E13: 9.515 | F13: 9.982 | G13: 8.519 | H13: 13.35 | I13: 19.512 | J13: 24.821 | K13: 40.946 | L13: 95.449 | M13: 129.556 | N13: 122.785 | O13: 154.163 | P13: 191.446 | Q13: 236.609 | R13: 269.019 | S13: 260.222 | T13: 281.814 | U13: 324.251 | V13: 412.693 | W13: 414.845 | X13: 498.61 | Y13: 610.272 | Z13: 760.867
B14: Interest income – other receivables | C14: 0 | D14: 0 | E14: 0 | F14: 0 | G14: 0 | H14: 2.116 | I14: 4.469 | J14: 10.651 | K14: 0 | L14: 32.108 | M14: 50.162 | N14: 78.734 | O14: 86.971 | P14: 96.609 | Q14: 111.465 | R14: 103.491 | S14: 103.816 | T14: 77.726 | U14: 73.117 | V14: 69.537 | W14: 70.815 | X14: 94.175 | Y14: 95.11 | Z14: 101.575
B15: Interest income and gains net of losses - financial instruments at fair value | C15: 43.469 | D15: 17.843 | E15: 11.483 | F15: 12.024 | G15: 25.715 | H15: 38.46 | I15: 92.053 | J15: 152.968 | K15: 194.9 | L15: 264.464 | M15: 308.569 | N15: 319.686 | O15: 271.194 | P15: 245.759 | Q15: 257.323 | R15: 198.753 | S15: 289.557 | T15: 351.149 | U15: 318.593 | V15: 328.692 | W15: 256.729 | X15: 296.219 | Y15: 391.787 | Z15: 414.813
B16: Other income at fair value | C16: 1.729 | D16: 0.02 | E16: -0.833 | F16: 2.923 | G16: 2.149 | H16: 0.767 | I16: 0.291 | J16: 0.373 | K16: -0.07 | L16: -10.959 | M16: -13.689 | N16: -4.499 | O16: 8.487 | P16: 19.474 | Q16: -5.859 | R16: 22.595 | S16: -12.881 | T16: -42.523 | U16: 4.132 | V16: -49.881 | W16: 30.939 | X16: 20.121 | Y16: 8.707 | Z16: -12.934
B17: Total interest income and gains net of losses on financial instruments | C17: 131.243 | D17: 91.884 | E17: 70.14 | F17: 89.655 | G17: 127.345 | H17: 184.893 | I17: 294.958 | J17: 439.55 | K17: 619.443 | L17: 853.013 | M17: 987.248 | N17: 1095.509 | O17: 1255.454 | P17: 1500.225 | Q17: 1732.699 | R17: 1951.334 | S17: 2280.248 | T17: 2383.307 | U17: 2473.807 | V17: 2493.681 | W17: 2732.136 | X17: 3128.743 | Y17: 3577.478 | Z17: 3996.326
B19: Credit and debit card income | C19: 61.723 | D19: 48.294 | E19: 62.435 | F19: 81.875 | G19: 83.617 | H19: 107.357 | I19: 130.469 | J19: 150.062 | K19: 189.506 | L19: 224.437 | M19: 244.229 | N19: 259.201 | O19: 265.38 | P19: 277.805 | Q19: 302.504 | R19: 342.168 | S19: 339.703 | T19: 344.4 | U19: 337.367 | V19: 359.107 | W19: 372.384 | X19: 392.568 | Y19: 435.96 | Z19: 519.366
B20: Late fees | C20: 9.086 | D20: 7.535 | E20: 6.353 | F20: 8.263 | G20: 9.651 | H20: 11.376 | I20: 13.315 | J20: 15.609 | K20: 20.701 | L20: 25.515 | M20: 17.917 | N20: 40.366 | O20: 36.359 | P20: 42.866 | Q20: 46.874 | R20: 54.589 | S20: 61.744 | T20: 70.49 | U20: 76.178 | V20: 79.071 | W20: 84.614 | X20: 90.193 | Y20: 101.839 | Z20: 108.359
B21: Insurance commission | C21: 0 | D21: 0 | E21: 0 | F21: 0 | G21: 0 | H21: 0 | I21: 0 | J21: 0 | K21: 0 | L21: 0 | M21: 0 | N21: 0 | O21: 0 | P21: 5.86 | Q21: 0 | R21: 0 | S21: 6.966 | T21: 6.427 | U21: 7.623 | V21: 8.082 | W21: 8.275 | X21: 8.493 | Y21: 9.182 | Z21: 9.58
B22: Other fee and commission income | C22: 14.103 | D22: 14.614 | E22: 17.158 | F22: 22.772 | G22: 24.45 | H22: 32.462 | I22: 42.165 | J22: 41.924 | K22: 47.617 | L22: 54.596 | M22: 57.473 | N22: 55.46 | O22: 61.474 | P22: 41.884 | Q22: 54.681 | R22: 56.82 | S22: 47.24 | T22: 44.067 | U22: 48.213 | V22: 49.354 | W22: 50.28 | X22: 48.473 | Y22: 48.257 | Z22: 52.235
B23: Customer Program ("NuSócios") | C23: 0 | D23: 0 | E23: 0 | F23: 0 | G23: 0 | H23: 0 | I23: 0 | J23: -11.18 | K23: 0 | L23: 0 | M23: 0 | N23: 0 | O23: 0 | P23: 0 | Q23: 0 | R23: 0 | S23: 0 | T23: 0 | U23: 0 | V23: 0 | W23: 0 | X23: 0 | Y23: 0 | Z23: 0
B24: Total fee and commission income | C24: 84.912 | D24: 70.443 | E24: 85.946 | F24: 112.91 | G24: 117.718 | H24: 151.195 | I24: 185.949 | J24: 196.415 | K24: 257.824 | L24: 304.548 | M24: 319.619 | N24: 355.027 | O24: 363.213 | P24: 368.415 | Q24: 404.059 | R24: 453.577 | S24: 455.653 | T24: 465.384 | U24: 469.381 | V24: 495.614 | W24: 515.553 | X24: 539.727 | Y24: 595.238 | Z24: 689.54

Sheet IFRS - Expenses breakdown
B2: Nu Holdings Ltd.
B3: Expenses Breakdown
B4: Amounts in million of US$
B5: Back to Contents
C8: 3-MONTH PERIOD ENDED
C9: 43921 | D9: 44012 | E9: 44104 | F9: 44196 | G9: 44286 | H9: 44377 | I9: 44469 | J9: 44561 | K9: 44651 | L9: 44742 | M9: 44834 | N9: 44926 | O9: 45016 | P9: 45107 | Q9: 45199 | R9: 45291 | S9: 45382 | T9: 45473 | U9: 45565 | V9: 45657 | W9: 45747 | X9: 45838 | Y9: 45930 | Z9: 46022
C10: US$ | D10: US$ | E10: US$ | F10: US$ | G10: US$ | H10: US$ | I10: US$ | J10: US$ | K10: US$ | L10: US$ | M10: US$ | N10: US$ | O10: US$ | P10: US$ | Q10: US$ | R10: US$ | S10: US$ | T10: US$ | U10: US$ | V10: US$ | W10: US$ | X10: US$ | Y10: US$ | Z10: US$
B11: Interest expense on deposits | C11: 26.113 | D11: 20.033 | E11: 19.108 | F11: 22.071 | G11: 25.416 | H11: 49.128 | I11: 91.098 | J11: 151.778 | K11: 247.218 | L11: 362.842 | M11: 430.356 | N11: 367.482 | O11: 395.116 | P11: 401.073 | Q11: 463.685 | R11: 463.965 | S11: 514.071 | T11: 550.281 | U11: 623.569 | V11: 654.306 | W11: 761.167 | X11: 920.052 | Y11: 1089.722 | Z11: 1105.603
B12: Interest expense on debt instruments and financing | C12: 0 | D12: 0 | E12: 0 | F12: 0 | G12: 0 | H12: 0 | I12: 0 | J12: 0 | K12: 0 | L12: 0 | M12: 0 | N12: 0 | O12: 5.729 | P12: 0 | Q12: 0 | R12: 0 | S12: 30.521 | T12: 38.909 | U12: 129.112 | V12: 60.888 | W12: 62.727 | X12: 52.582 | Y12: 121.081 | Z12: 193.303
B13: Other interest and similar expenses | C13: 7.117 | D13: 5.288 | E13: 4.876 | F13: 9.318 | G13: 6.327 | H13: 8.108 | I13: 10.295 | J13: 25.194 | K13: 25.785 | L13: 44.658 | M13: 29.533 | N13: 40.029 | O13: 39.367 | P13: 52.353 | Q13: 73.964 | R13: 141.673 | S13: 116.123 | T13: 76.001 | U13: 8.278 | V13: 32.8 | W13: 72.31 | X13: 57.355 | Y13: 64.908 | Z13: 77.87
B14: Total interest and other financial expenses | C14: 33.23 | D14: 25.321 | E14: 23.984 | F14: 31.389 | G14: 31.743 | H14: 57.236 | I14: 101.393 | J14: 176.972 | K14: 273.003 | L14: 407.5 | M14: 459.889 | N14: 407.511 | O14: 440.212 | P14: 453.426 | Q14: 537.649 | R14: 605.638 | S14: 660.715 | T14: 665.191 | U14: 760.959 | V14: 747.994 | W14: 896.204 | X14: 1029.989 | Y14: 1275.711 | Z14: 1376.776 | AA14: =SUM(W14:Z14) -> 4578.68 | AB14: =SUM('IFRS - Statement of Income'!W15:Z15) -> -4578.68 | AC14: =AA14+AB14 -> 0
B16: Payments and network costs | C16: 16.918 | D16: 11.108 | E16: 19.42 | F16: 24.02 | G16: 15.167 | H16: 17.165 | I16: 10.672 | J16: 15.85 | K16: 14.543 | L16: 24.821 | M16: 22.571 | N16: 27.015 | O16: 25.246 | P16: 13.889 | Q16: 19.946 | R16: 17.071 | S16: 20.135 | T16: 19.198 | U16: 23.128 | V16: 21.112 | W16: 17.206 | X16: 14.174 | Y16: 20.971 | Z16: 55.268
B17: Rewards expenses | C17: 6.674 | D17: 8.292 | E17: 6.603 | F17: 8.055 | G17: 7.724 | H17: 8.753 | I17: 10.255 | J17: 10.153 | K17: 10.107 | L17: 10.932 | M17: 10.487 | N17: 10.896 | O17: 12.116 | P17: 13.717 | Q17: 15.376 | R17: 17.095 | S17: 15.746 | T17: 19.126 | U17: 15.813 | V17: 17.815 | W17: 19.71 | X17: 24.092 | Y17: 33.647 | Z17: 60.72
B18: Financial system expenses | C18: 0 | D18: 0 | E18: 0 | F18: 0 | G18: 0 | H18: 0 | I18: 0 | J18: 0 | K18: 0 | L18: 0 | M18: 0 | N18: 0 | O18: 3.873 | P18: 0 | Q18: 0 | R18: 0 | S18: 5.467 | T18: 7.349 | U18: 1.198 | V18: 0.981 | W18: 1.247 | X18: 3.433 | Y18: 4.479 | Z18: 6.351
B19: Other transactional expenses | C19: 9.544 | D19: 3.204 | E19: 5.887 | F19: 7.09 | G19: 3.458 | H19: 3.864 | I19: 7.633 | J19: 6.425 | K19: 9.798 | L19: 12.283 | M19: 11.417 | N19: 11.557 | O19: 11.543 | P19: 15.191 | Q19: 21.452 | R19: 29.415 | S19: 21.6 | T19: 18.637 | U19: 19.315 | V19: 33.704 | W19: 20.325 | X19: 36.612 | Y19: 45.893 | Z19: 2.055
B20: Total transactional expenses | C20: 33.136 | D20: 22.604 | E20: 31.91 | F20: 39.165 | G20: 26.349 | H20: 29.782 | I20: 28.56 | J20: 32.428 | K20: 34.448 | L20: 48.036 | M20: 44.475 | N20: 49.468 | O20: 52.778 | P20: 42.797 | Q20: 56.774 | R20: 63.581 | S20: 62.948 | T20: 64.31 | U20: 59.454 | V20: 73.612 | W20: 58.488 | X20: 78.311 | Y20: 104.99 | Z20: 124.394 | AA20: =SUM(W20:Z20) -> 366.183 | AB20: =SUM('IFRS - Statement of Income'!W16:Z16) -> -366.183 | AC20: =AA20+AB20 -> 0
B22: Customer support and operations
B23: Infrastructure and data processing costs | C23: -17.664 | D23: -8.842 | E23: -9.8 | F23: -9.419 | G23: -11.794 | H23: -13.822 | I23: -18.779 | J23: -26.533 | K23: -19.394 | L23: -29.462 | M23: -37.521 | N23: -45.786 | O23: -40.167 | P23: -45.77 | Q23: -44.332 | R23: -56.382 | S23: -58.595 | T23: -63.056 | U23: -49.66 | V23: -62.534 | W23: -59.141 | X23: -63.092 | Y23: -67.57 | Z23: -57.492
B24: Credit analysis and collection costs | C24: -3.13 | D24: -4.117 | E24: -8.701 | F24: -5.789 | G24: -5.326 | H24: -7.76 | I24: -9.031 | J24: -11.909 | K24: -8.037 | L24: -12.371 | M24: -15.358 | N24: -18.473 | O24: -17.667 | P24: -20.773 | Q24: -25.554 | R24: -25.299 | S24: -19.538 | T24: -31.577 | U24: -29.219 | V24: -31.53 | W24: -24.111 | X24: -40.286 | Y24: -30.865 | Z24: -32.715
B25: Customer services | C25: -11.713 | D25: -8.951 | E25: -6.237 | F25: -7.174 | G25: -8.22 | H25: -9.868 | I25: -14.628 | J25: -15.406 | K25: -19.993 | L25: -19.074 | M25: -17.697 | N25: -17.674 | O25: -22.257 | P25: -17.147 | Q25: -20.001 | R25: -21.461 | S25: -30.025 | T25: -22.546 | U25: -19.285 | V25: -20.759 | W25: -26.813 | X25: -15.031 | Y25: -22.005 | Z25: -23.535
B26: Salaries and associated benefits | C26: -3.617 | D26: -3.468 | E26: -3.305 | F26: -3.472 | G26: -3.983 | H26: -4.568 | I26: -5.61 | J26: -5.737 | K26: -8.957 | L26: -11.399 | M26: -11.891 | N26: -16.414 | O26: -17.215 | P26: -18.765 | Q26: -19.957 | R26: -16.541 | S26: -19.529 | T26: -19.549 | U26: -19.135 | V26: -16.04 | W26: -16.374 | X26: -18.813 | Y26: -20.246 | Z26: -22.296
B27: Credit and debit card issuance costs | C27: -3.195 | D27: -0.507 | E27: -0.367 | F27: -2.005 | G27: -2.154 | H27: -4.206 | I27: -2.179 | J27: -5.172 | K27: -3.599 | L27: -2.795 | M27: -4.313 | N27: -2.467 | O27: -4.898 | P27: -4.032 | Q27: -8.108 | R27: -10.099 | S27: -7.763 | T27: -9.835 | U27: -3.496 | V27: -10.309 | W27: -10.823 | X27: -8.06 | Y27: -15.846 | Z27: -10.212
B28: Share-based compensation | C28: 0 | D28: 0 | E28: 0 | F28: 0 | G28: 0 | H28: 0 | I28: 0 | J28: 0 | K28: 0 | L28: 0 | M28: 0 | N28: 0 | O28: 0 | P28: 0 | Q28: -1.551 | R28: -1.219 | S28: -3.759 | T28: -4.443 | U28: -1.867 | V28: -1.986 | W28: -1.321 | X28: -1.922 | Y28: -1.583 | Z28: -1.019
B29: Specialized services expenses | C29: 0 | D29: 0 | E29: 0 | F29: 0 | G29: 0 | H29: 0 | I29: 0 | J29: 0 | K29: 0 | L29: 0 | M29: 0 | N29: 0 | O29: 0 | P29: 0 | Q29: 0 | R29: 0 | S29: 0 | T29: 0 | U29: 0 | V29: 0 | W29: 0 | X29: 0 | Y29: 0 | Z29: 0
B30: Other personnel costs | C30: -0.527 | D30: -0.485 | E30: -0.41 | F30: -0.405 | G30: -0.426 | H30: -0.513 | I30: -0.63 | J30: -0.684 | K30: -1.025 | L30: -1.693 | M30: -2.357 | N30: -3.478 | O30: -3.598 | P30: -4.012 | Q30: -4.032 | R30: -4.033 | S30: -4.939 | T30: -5.293 | U30: -5.591 | V30: -5.195 | W30: -5.155 | X30: -5.736 | Y30: -6.367 | Z30: -5.73
B31: Depreciation and amortization | C31: 0 | D31: 0 | E31: 0 | F31: -0.079 | G31: -0.124 | H31: -0.14 | I31: -0.703 | J31: -0.25 | K31: -0.566 | L31: -0.815 | M31: -1.074 | N31: -1.51 | O31: -1.978 | P31: -2.777 | Q31: -3.722 | R31: -4.595 | S31: -6.431 | T31: -6.589 | U31: -6.921 | V31: -7.544 | W31: -7.716 | X31: -8.468 | Y31: -10.315 | Z31: -10.972
B32: Advertising and marketing | C32: 0 | D32: 0 | E32: 0 | F32: 0 | G32: 0 | H32: 0 | I32: 0 | J32: 0 | K32: 0 | L32: 0 | M32: 0 | N32: 0 | O32: 0 | P32: 0 | Q32: 0 | R32: 0 | S32: 0 | T32: 0 | U32: 0 | V32: 0 | W32: 0 | X32: 0 | Y32: 0 | Z32: 0
B33: Taxes on financial income | C33: 0 | D33: 0 | E33: 0 | F33: 0 | G33: 0 | H33: 0 | I33: 0 | J33: 0 | K33: 0 | L33: 0 | M33: 0 | N33: 0 | O33: 0 | P33: 0 | Q33: 0 | R33: 0 | S33: 0 | T33: 0 | U33: 0 | V33: 0 | W33: 0 | X33: 0 | Y33: 0 | Z33: 0
B34: Others | C34: -0.253 | D34: -0.057 | E34: -0.11 | F34: -0.151 | G34: -0.103 | H34: -0.091 | I34: -0.089 | J34: -0.071 | K34: 0 | L34: -0.094 | M34: -0.038 | N34: -0.038 | O34: -0.035 | P34: -0.033 | Q34: -0.038 | R34: -0.034 | S34: -0.033 | T34: -0.029 | U34: -0.022 | V34: -0.021 | W34: -0.021 | X34: -0.026 | Y34: -0.046 | Z34: -0.037
B35: Total | C35: -40.099 | D35: -26.427 | E35: -28.93 | F35: -28.494 | G35: -32.13 | H35: -40.968 | I35: -51.649 | J35: -65.762 | K35: -61.571 | L35: -77.703 | M35: -90.249 | N35: -105.84 | O35: -107.815 | P35: -113.309 | Q35: -127.295 | R35: -139.663 | S35: -150.612 | T35: -162.917 | U35: -135.196 | V35: -155.918 | W35: -151.475 | X35: -161.434 | Y35: -174.843 | Z35: -164.008 | AA35: =SUM(W35:Z35) -> -651.76 | AB35: =sum('IFRS - Statement of Income'!W23:Z23) -> -651.76 | AC35: =AB35-AA35 -> 0
B37: General and administrative expenses
B38: Infrastructure and data processing costs | C38: -7.912 | D38: -6.597 | E38: -8.112 | F38: -6.49 | G38: -9.522 | H38: -12.708 | I38: -18.599 | J38: -23.004 | K38: -28.587 | L38: -34.496 | M38: -42.167 | N38: -39.091 | O38: -45.949 | P38: -41.871 | Q38: -38.767 | R38: -47.97 | S38: -47.435 | T38: -47.679 | U38: -43.706 | V38: -56.244 | W38: -48.165 | X38: -53.693 | Y38: -62.13 | Z38: -90.932
B39: Credit analysis and collection costs | C39: -3.834 | D39: -3.862 | E39: -0.061 | F39: -4.595 | G39: -3.651 | H39: -4.826 | I39: -7.659 | J39: -9.707 | K39: -8.82 | L39: -10.902 | M39: -11.02 | N39: -9.031 | O39: -9.706 | P39: -8.643 | Q39: -10.559 | R39: -12.408 | S39: -9.516 | T39: -8.168 | U39: -9.772 | V39: -8.538 | W39: -8.17 | X39: -8.42 | Y39: -8.83 | Z39: -7.26
B40: Customer services | C40: -1.785 | D40: -1.475 | E40: -0.948 | F40: -1.28 | G40: -1.229 | H40: -1.606 | I40: -2.203 | J40: -1.885 | K40: -2.013 | L40: -2.708 | M40: -2.534 | N40: -2.304 | O40: -1.926 | P40: -1.922 | Q40: -1.852 | R40: -1.791 | S40: -1.659 | T40: -1.744 | U40: -1.485 | V40: -1.454 | W40: -1.687 | X40: -1.443 | Y40: -1.392 | Z40: -0.633
B41: Salaries and associated benefits | C41: -25.76 | D41: -20.984 | E41: -23.18 | F41: -25.136 | G41: -31.764 | H41: -36.067 | I41: -59.303 | J41: -58.581 | K41: -71.003 | L41: -70.414 | M41: -73.827 | N41: -59.873 | O41: -64.096 | P41: -71.356 | Q41: -72.339 | R41: -92.768 | S41: -92.301 | T41: -84.734 | U41: -91.6 | V41: -81.275 | W41: -83.041 | X41: -87.615 | Y41: -97.45 | Z41: -141.194
B42: Credit and debit card issuance costs | C42: -7.892 | D42: -1.172 | E42: -1.048 | F42: -1.71 | G42: -3.952 | H42: -5.684 | I42: -8.165 | J42: -7.644 | K42: -9.249 | L42: -12.953 | M42: -13.144 | N42: -8.343 | O42: -14.437 | P42: -12.38 | Q42: -14.597 | R42: -13.982 | S42: -10.371 | T42: -12.231 | U42: -7.542 | V42: -13.509 | W42: -12.932 | X42: -13.125 | Y42: -17.304 | Z42: -12.26
B43: Share-based compensation | C43: -8.486 | D43: -7.922 | E43: -13.254 | F43: -26.611 | G43: -48.897 | H43: -42.502 | I43: -43.913 | J43: -90.133 | K43: -77.717 | L43: -61.076 | M43: -78.857 | N43: -68.8 | O43: -59.505 | P43: -66.587 | Q43: -70.929 | R43: -54.748 | S43: -99.268 | T43: -111.458 | U43: -65.569 | V43: -75.136 | W43: -70.429 | X43: -95.459 | Y43: -74.489 | Z43: -73.572
B44: Share-based compensation - contingent share award termination (note 10b)) (i) | C44: 0 | D44: 0 | E44: 0 | F44: 0 | G44: 0 | H44: 0 | I44: 0 | J44: 0 | K44: 0 | L44: 0 | M44: 0 | N44: -355.573 | O44: 0 | P44: 0 | Q44: 0 | R44: 0 | S44: 0 | T44: 0 | U44: 0 | V44: 0 | W44: 0 | X44: 0 | Y44: 0 | Z44: 0
B45: Specialized services expenses | C45: -3.406 | D45: -4.6 | E45: -3.182 | F45: -6.241 | G45: -7.377 | H45: -6.238 | I45: -6.212 | J45: -9.373 | K45: -9.633 | L45: -9.529 | M45: -7.141 | N45: -13.539 | O45: -3.248 | P45: -12.683 | Q45: -26.367 | R45: -19.106 | S45: -16.089 | T45: -12.152 | U45: -15.288 | V45: -33.702 | W45: -18.866 | X45: -29.118 | Y45: -29.673 | Z45: -24.804
B46: Other personnel costs | C46: -3.847 | D46: -1.935 | E46: -1.862 | F46: -2.477 | G46: -2.336 | H46: -3.653 | I46: -5.092 | J46: -7.371 | K46: -8.458 | L46: -8.717 | M46: -12.402 | N46: -11.917 | O46: -11.591 | P46: -9.965 | Q46: -10.971 | R46: -13.724 | S46: -12.945 | T46: -13.394 | U46: -14.585 | V46: -12.915 | W46: -13.631 | X46: -15.764 | Y46: -18.171 | Z46: -22.578
B47: Depreciation and amortization | C47: -0.56 | D47: -2.333 | E47: -0.89 | F47: -3.568 | G47: -2.383 | H47: -2.595 | I47: -4.951 | J47: -6.193 | K47: -7.089 | L47: -9.618 | M47: -6.537 | N47: -8.372 | O47: -11.201 | P47: -11.2 | Q47: -15.472 | R47: -11.95 | S47: -12.034 | T47: -11.744 | U47: -12.348 | V47: -13.517 | W47: -13.606 | X47: -14.602 | Y47: -15.255 | Z47: -17.034
B48: Advertising and marketing | C48: 0 | D48: 0 | E48: 0 | F48: 0 | G48: 0 | H48: 0 | I48: 0 | J48: 0 | K48: 0 | L48: 0 | M48: 0 | N48: 0 | O48: 0 | P48: 0 | Q48: 0 | R48: 0 | S48: 0 | T48: 0 | U48: 0 | V48: 0 | W48: 0 | X48: 0 | Y48: 0 | Z48: 0
B49: Taxes on financial income | C49: 0 | D49: 0 | E49: 0 | F49: 0 | G49: 0 | H49: 0 | I49: 0 | J49: 0 | K49: 0 | L49: 0 | M49: 0 | N49: 0 | O49: 0 | P49: 0 | Q49: 0 | R49: 0 | S49: 0 | T49: 0 | U49: 0 | V49: 0 | W49: 0 | X49: 0 | Y49: 0 | Z49: 0
B50: Others | C50: -7.142 | D50: -6.099 | E50: -4.251 | F50: -3.525 | G50: -4.737 | H50: -6.416 | I50: -10.43 | J50: -10.34 | K50: -22.539 | L50: -9.092 | M50: -14.149 | N50: -20.033 | O50: -15.222 | P50: -19.801 | Q50: -2.411 | R50: -16.29 | S50: -24.434 | T50: -23.251 | U50: -22.811 | V50: -22.483 | W50: -19.296 | X50: -22.014 | Y50: -24.568 | Z50: -49.855
B51: Total | C51: -70.624 | D51: -56.979 | E51: -56.788 | F51: -81.633 | G51: -115.848 | H51: -122.295 | I51: -166.527 | J51: -224.231 | K51: -245.108 | L51: -229.505 | M51: -261.778 | N51: -596.876 | O51: -236.881 | P51: -256.408 | Q51: -264.264 | R51: -284.737 | S51: -326.052 | T51: -326.555 | U51: -284.706 | V51: -318.773 | W51: -289.823 | X51: -341.253 | Y51: -349.262 | Z51: -440.122 | AA51: =SUM(W51:Z51) -> -1420.46 | AB51: =sum('IFRS - Statement of Income'!W24:Z24) -> -1420.46 | AC51: =AB51-AA51 -> 0
B53: Marketing expenses
B54: Infrastructure and data processing costs | C54: 0 | D54: 0 | E54: 0 | F54: 0 | G54: 0 | H54: 0 | I54: 0 | J54: 0 | K54: 0 | L54: 0 | M54: 0 | N54: 0 | O54: 0 | P54: 0 | Q54: 0 | R54: 0 | S54: 0 | T54: 0 | U54: 0 | V54: 0 | W54: 0 | X54: 0 | Y54: 0 | Z54: 0
B55: Credit analysis and collection costs | C55: 0 | D55: 0 | E55: 0 | F55: 0 | G55: 0 | H55: 0 | I55: 0 | J55: 0 | K55: 0 | L55: 0 | M55: 0 | N55: 0 | O55: 0 | P55: 0 | Q55: 0 | R55: 0 | S55: 0 | T55: 0 | U55: 0 | V55: 0 | W55: 0 | X55: 0 | Y55: 0 | Z55: 0
B56: Customer services | C56: 0 | D56: 0 | E56: 0 | F56: 0 | G56: 0 | H56: 0 | I56: 0 | J56: 0 | K56: 0 | L56: 0 | M56: 0 | N56: 0 | O56: 0 | P56: 0 | Q56: 0 | R56: 0 | S56: 0 | T56: 0 | U56: 0 | V56: 0 | W56: 0 | X56: 0 | Y56: 0 | Z56: 0
B57: Salaries and associated benefits | C57: -0.57 | D57: -0.361 | E57: -0.938 | F57: -0.938 | G57: -0.819 | H57: -1.431 | I57: -2.317 | J57: -2.955 | K57: -3.158 | L57: -3.781 | M57: -4.063 | N57: -4.428 | O57: -5.272 | P57: -4.864 | Q57: -5.717 | R57: -5.141 | S57: -4.741 | T57: -4.453 | U57: -4.75 | V57: -4.366 | W57: -4.576 | X57: -4.869 | Y57: -5.129 | Z57: -5.235
B58: Credit and debit card issuance costs | C58: 0 | D58: 0 | E58: 0 | F58: 0 | G58: 0 | H58: 0 | I58: 0 | J58: 0 | K58: 0 | L58: 0 | M58: 0 | N58: 0 | O58: 0 | P58: 0 | Q58: 0 | R58: 0 | S58: 0 | T58: 0 | U58: 0 | V58: 0 | W58: 0 | X58: 0 | Y58: 0 | Z58: 0
B59: Share-based compensation | C59: 0 | D59: 0 | E59: 0 | F59: 0 | G59: 0 | H59: 0 | I59: 0 | J59: 0 | K59: 0 | L59: 0 | M59: 0 | N59: 0 | O59: 0 | P59: 0 | Q59: -0.644 | R59: -0.431 | S59: -2.498 | T59: -3.263 | U59: -1.689 | V59: -1.733 | W59: -2.345 | X59: -3.292 | Y59: -2.234 | Z59: -1.791
B60: Specialized services expenses | C60: 0 | D60: 0 | E60: 0 | F60: 0 | G60: 0 | H60: 0 | I60: 0 | J60: 0 | K60: 0 | L60: 0 | M60: 0 | N60: 0 | O60: 0 | P60: 0 | Q60: 0 | R60: 0 | S60: 0 | T60: 0 | U60: 0 | V60: 0 | W60: 0 | X60: 0 | Y60: 0 | Z60: 0
B61: Other personnel costs | C61: -0.031 | D61: -0.015 | E61: -0.047 | F61: -0.047 | G61: -0.378 | H61: -0.053 | I61: -0.076 | J61: 0.23 | K61: -0.279 | L61: -0.254 | M61: -0.442 | N61: -0.45 | O61: -0.5 | P61: -0.621 | Q61: -0.61 | R61: -0.567 | S61: -0.543 | T61: -0.546 | U61: -0.542 | V61: -0.57 | W61: -0.543 | X61: -0.586 | Y61: -0.628 | Z61: -0.486
B62: Depreciation and amortization | C62: 0 | D62: 0 | E62: 0 | F62: 0 | G62: 0 | H62: 0 | I62: 0 | J62: 0 | K62: 0 | L62: 0 | M62: 0 | N62: 0 | O62: 0 | P62: 0 | Q62: 0 | R62: 0 | S62: 0 | T62: 0 | U62: 0 | V62: 0 | W62: 0 | X62: 0 | Y62: 0 | Z62: 0
B63: Branding and advertising | C63: -5.492 | D63: -0.969 | E63: -3.103 | F63: -6.915 | G63: -3.67 | H63: -13.147 | I63: -23.175 | J63: -31.783 | K63: -24.171 | L63: -32.173 | M63: -33.598 | N63: -46.2 | O63: -13.5 | P63: -28.438 | Q63: -39.512 | R63: 0 | S63: -39.045 | T63: -39.489 | U63: -92.837 | V63: -45.331 | W63: -36.633 | X63: -58.6 | Y63: -62.349 | Z63: -113.526
B64: Taxes on financial income | C64: 0 | D64: 0 | E64: 0 | F64: 0 | G64: 0 | H64: 0 | I64: 0 | J64: 0 | K64: 0 | L64: 0 | M64: 0 | N64: 0 | O64: 0 | P64: 0 | Q64: 0 | R64: 0 | S64: 0 | T64: 0 | U64: 0 | V64: 0 | W64: 0 | X64: 0 | Y64: 0 | Z64: 0
B65: Others | C65: 0 | D65: 0 | E65: 0 | F65: 0 | G65: 0 | H65: 0 | I65: 0 | J65: 0 | K65: 0 | L65: 0 | M65: 0 | N65: 0 | O65: 0 | P65: 0 | Q65: 0 | R65: 0 | S65: 0 | T65: 0 | U65: 0 | V65: 0 | W65: 0 | X65: 0 | Y65: 0 | Z65: 0
B66: Total | C66: -6.093 | D66: -1.345 | E66: -4.088 | F66: -7.9 | G66: -4.867 | H66: -14.631 | I66: -25.568 | J66: -34.508 | K66: -27.608 | L66: -36.208 | M66: -38.103 | N66: -51.078 | O66: -19.272 | P66: -33.923 | Q66: -46.483 | R66: -71.344 | S66: -46.827 | T66: -47.751 | U66: -99.818 | V66: -52 | W66: -44.097 | X66: -67.347 | Y66: -70.34 | Z66: -121.038 | AA66: =SUM(W66:Z66) -> -302.822 | AB66: =sum('IFRS - Statement of Income'!W27:Z27) -> -302.822 | AC66: =AB66-AA66 -> 0
B68: Other expenses
B69: Infrastructure and data processing costs | C69: 0 | D69: 0 | E69: 0 | F69: 0 | G69: 0 | H69: 0 | I69: 0 | J69: 0 | K69: 0 | L69: 0 | M69: 0 | N69: 0 | O69: 0 | P69: 0 | Q69: 0 | R69: 0 | S69: 0 | T69: 0 | U69: 0 | V69: 0 | W69: 0 | X69: 0 | Y69: 0 | Z69: 0 | AA69: =SUM(W69:Z69) -> 0
B70: Credit analysis and collection costs | C70: 0 | D70: 0 | E70: 0 | F70: 0 | G70: 0 | H70: 0 | I70: 0 | J70: 0 | K70: 0 | L70: 0 | M70: 0 | N70: 0 | O70: 0 | P70: 0 | Q70: 0 | R70: 0 | S70: 0 | T70: 0 | U70: 0 | V70: 0 | W70: 0 | X70: 0 | Y70: 0 | Z70: 0 | AA70: =SUM(W70:Z70) -> 0
B71: Customer services | C71: 0 | D71: 0 | E71: 0 | F71: 0 | G71: 0 | H71: 0 | I71: 0 | J71: 0 | K71: 0 | L71: 0 | M71: 0 | N71: 0 | O71: 0 | P71: 0 | Q71: 0 | R71: 0 | S71: 0 | T71: 0 | U71: 0 | V71: 0 | W71: 0 | X71: 0 | Y71: 0 | Z71: 0 | AA71: =SUM(W71:Z71) -> 0
B72: Salaries and associated benefits | C72: 0 | D72: 0 | E72: 0 | F72: 0 | G72: 0 | H72: 0 | I72: 0 | J72: 0 | K72: 0 | L72: 0 | M72: 0 | N72: 0 | O72: 0 | P72: 0 | Q72: 0 | R72: 0 | S72: 0 | T72: 0 | U72: 0 | V72: 0 | W72: 0 | X72: 0 | Y72: 0 | Z72: 0 | AA72: =SUM(W72:Z72) -> 0
B73: Credit and debit card issuance costs | C73: 0 | D73: 0 | E73: 0 | F73: 0 | G73: 0 | H73: 0 | I73: 0 | J73: 0 | K73: 0 | L73: 0 | M73: 0 | N73: 0 | O73: 0 | P73: 0 | Q73: 0 | R73: 0 | S73: 0 | T73: 0 | U73: 0 | V73: 0 | W73: 0 | X73: 0 | Y73: 0 | Z73: 0 | AA73: =SUM(W73:Z73) -> 0
B74: Share-based compensation | C74: 0 | D74: 0 | E74: 0 | F74: 0 | G74: 0 | H74: 0 | I74: 0 | J74: 0 | K74: 0 | L74: 0 | M74: 0 | N74: 0 | O74: 0 | P74: 0 | Q74: 0 | R74: 0 | S74: 0 | T74: 0 | U74: 0 | V74: 0 | W74: 0 | X74: 0 | Y74: 0 | Z74: 0 | AA74: =SUM(W74:Z74) -> 0
B75: Specialized services expenses | C75: 0 | D75: 0 | E75: 0 | F75: 0 | G75: 0 | H75: 0 | I75: 0 | J75: 0 | K75: 0 | L75: 0 | M75: 0 | N75: 0 | O75: 0 | P75: 0 | Q75: 0 | R75: 0 | S75: 0 | T75: 0 | U75: 0 | V75: 0 | W75: 0 | X75: 0 | Y75: 0 | Z75: 0 | AA75: =SUM(W75:Z75) -> 0
B76: Other personnel costs | C76: 0 | D76: 0 | E76: 0 | F76: 0 | G76: 0 | H76: 0 | I76: 0 | J76: 0 | K76: 0 | L76: 0 | M76: 0 | N76: 0 | O76: 0 | P76: 0 | Q76: 0 | R76: 0 | S76: 0 | T76: 0 | U76: 0 | V76: 0 | W76: 0 | X76: 0 | Y76: 0 | Z76: 0 | AA76: =SUM(W76:Z76) -> 0
B77: Depreciation and amortization | C77: 0 | D77: 0 | E77: 0 | F77: 0 | G77: 0 | H77: 0 | I77: 0 | J77: 0 | K77: 0 | L77: 0 | M77: 0 | N77: 0 | O77: 0 | P77: 0 | Q77: 0 | R77: 0 | S77: 0 | T77: 0 | U77: 0 | V77: 0 | W77: 0 | X77: 0 | Y77: 0 | Z77: 0 | AA77: =SUM(W77:Z77) -> 0
B78: Advertising and marketing | C78: 0 | D78: 0 | E78: 0 | F78: 0 | G78: 0 | H78: 0 | I78: 0 | J78: 0 | K78: 0 | L78: 0 | M78: 0 | N78: 0 | O78: 0 | P78: 0 | Q78: 0 | R78: 0 | S78: 0 | T78: 0 | U78: 0 | V78: 0 | W78: 0 | X78: 0 | Y78: 0 | Z78: 0 | AA78: =SUM(W78:Z78) -> 0
B79: Taxes on financial income | C79: 0 | D79: 0 | E79: 0 | F79: 0 | G79: 0 | H79: 0 | I79: 0 | J79: 0 | K79: 0 | L79: 0 | M79: 0 | N79: 0 | O79: -41.712 | P79: 0 | Q79: 0 | R79: 0 | S79: -81.52 | T79: -86.024 | U79: -85.332 | V79: -89.114 | W79: -94.725 | X79: -106.882 | Y79: -116.709 | Z79: -123.973 | AA79: =SUM(W79:Z79) -> -442.289
B80: Others | C80: -17.648 | D80: -5.692 | E80: -2.106 | F80: 15.911 | G80: -16.199 | H80: 4.954 | I80: -1.962 | J80: 9.11 | K80: -27.458 | L80: -44.729 | M80: -31.792 | N80: -46.285 | O80: -1.573 | P80: -54.366 | Q80: -65.242 | R80: -87.538 | S80: -2.14 | T80: -12.623 | U80: -28.07 | V80: -21.769 | W80: -13.27 | X80: -5.407 | Y80: -13.186 | Z80: -33.79 | AA80: =SUM(W80:Z80) -> -65.653
B81: Total | C81: -17.648 | D81: -5.692 | E81: -2.106 | F81: 15.911 | G81: -16.199 | H81: 4.954 | I81: -1.962 | J81: 9.11 | K81: -27.458 | L81: -44.729 | M81: -31.792 | N81: -46.285 | O81: -43.285 | P81: -54.366 | Q81: -65.242 | R81: -87.538 | S81: -83.66 | T81: -98.647 | U81: -113.402 | V81: -110.883 | W81: -107.995 | X81: -112.289 | Y81: -129.895 | Z81: -157.763 | AA81: =SUM(W81:Z81) -> -507.942 | AB81: =sum('IFRS - Statement of Income'!W28:Z28) -> -507.942 | AC81: =AB81-AA81 -> 0
B83: Other income
B84: Infrastructure and data processing costs | C84: 0 | D84: 0 | E84: 0 | F84: 0 | G84: 0 | H84: 0 | I84: 0 | J84: 0 | K84: 0 | L84: 0 | M84: 0 | N84: 0 | O84: 0 | P84: 0 | Q84: 0 | R84: 0 | S84: 0 | T84: 0 | U84: 0 | V84: 0 | W84: 0 | X84: 0 | Y84: 0 | Z84: 0
B85: Credit analysis and collection costs | C85: 0 | D85: 0 | E85: 0 | F85: 0 | G85: 0 | H85: 0 | I85: 0 | J85: 0 | K85: 0 | L85: 0 | M85: 0 | N85: 0 | O85: 0 | P85: 0 | Q85: 0 | R85: 0 | S85: 0 | T85: 0 | U85: 0 | V85: 0 | W85: 0 | X85: 0 | Y85: 0 | Z85: 0
B86: Customer services | C86: 0 | D86: 0 | E86: 0 | F86: 0 | G86: 0 | H86: 0 | I86: 0 | J86: 0 | K86: 0 | L86: 0 | M86: 0 | N86: 0 | O86: 0 | P86: 0 | Q86: 0 | R86: 0 | S86: 0 | T86: 0 | U86: 0 | V86: 0 | W86: 0 | X86: 0 | Y86: 0 | Z86: 0
B87: Salaries and associated benefits | C87: 0 | D87: 0 | E87: 0 | F87: 0 | G87: 0 | H87: 0 | I87: 0 | J87: 0 | K87: 0 | L87: 0 | M87: 0 | N87: 0 | O87: 0 | P87: 0 | Q87: 0 | R87: 0 | S87: 0 | T87: 0 | U87: 0 | V87: 0 | W87: 0 | X87: 0 | Y87: 0 | Z87: 0
B88: Credit and debit card issuance costs | C88: 0 | D88: 0 | E88: 0 | F88: 0 | G88: 0 | H88: 0 | I88: 0 | J88: 0 | K88: 0 | L88: 0 | M88: 0 | N88: 0 | O88: 0 | P88: 0 | Q88: 0 | R88: 0 | S88: 0 | T88: 0 | U88: 0 | V88: 0 | W88: 0 | X88: 0 | Y88: 0 | Z88: 0
B89: Share-based compensation | C89: 0 | D89: 0 | E89: 0 | F89: 0 | G89: 0 | H89: 0 | I89: 0 | J89: 0 | K89: 0 | L89: 0 | M89: 0 | N89: 0 | O89: 0 | P89: 0 | Q89: 0 | R89: 0 | S89: 0 | T89: 0 | U89: 0 | V89: 0 | W89: 0 | X89: 0 | Y89: 0 | Z89: 0
B90: Specialized services expenses | C90: 0 | D90: 0 | E90: 0 | F90: 0 | G90: 0 | H90: 0 | I90: 0 | J90: 0 | K90: 0 | L90: 0 | M90: 0 | N90: 0 | O90: 0 | P90: 0 | Q90: 0 | R90: 0 | S90: 0 | T90: 0 | U90: 0 | V90: 0 | W90: 0 | X90: 0 | Y90: 0 | Z90: 0
B91: Other personnel costs | C91: 0 | D91: 0 | E91: 0 | F91: 0 | G91: 0 | H91: 0 | I91: 0 | J91: 0 | K91: 0 | L91: 0 | M91: 0 | N91: 0 | O91: 0 | P91: 0 | Q91: 0 | R91: 0 | S91: 0 | T91: 0 | U91: 0 | V91: 0 | W91: 0 | X91: 0 | Y91: 0 | Z91: 0
B92: Depreciation and amortization | C92: 0 | D92: 0 | E92: 0 | F92: 0 | G92: 0 | H92: 0 | I92: 0 | J92: 0 | K92: 0 | L92: 0 | M92: 0 | N92: 0 | O92: 0 | P92: 0 | Q92: 0 | R92: 0 | S92: 0 | T92: 0 | U92: 0 | V92: 0 | W92: 0 | X92: 0 | Y92: 0 | Z92: 0
B93: Advertising and marketing | C93: 0 | D93: 0 | E93: 0 | F93: 0 | G93: 0 | H93: 0 | I93: 0 | J93: 0 | K93: 0 | L93: 0 | M93: 0 | N93: 0 | O93: 0 | P93: 0 | Q93: 0 | R93: 0 | S93: 0 | T93: 0 | U93: 0 | V93: 0 | W93: 0 | X93: 0 | Y93: 0 | Z93: 0
B94: Taxes on financial income | C94: 0 | D94: 0 | E94: 0 | F94: 0 | G94: 0 | H94: 0 | I94: 0 | J94: 0 | K94: 0 | L94: 0 | M94: 0 | N94: 0 | O94: 0 | P94: 0 | Q94: 0 | R94: 0 | S94: 0 | T94: 0 | U94: 0 | V94: 0 | W94: 0 | X94: 0 | Y94: 0 | Z94: 0
B95: Others | C95: 0 | D95: 0 | E95: 0 | F95: 0 | G95: 0 | H95: 0 | I95: 0 | J95: 0 | K95: 0 | L95: 0 | M95: 0 | N95: 0 | O95: 0 | P95: 0 | Q95: 0 | R95: 0 | S95: 4.169 | T95: 1.86576 | U95: 8.281 | V95: 41.69 | W95: 70.14 | X95: 14.732 | Y95: 27.267 | Z95: 17.951 | AA95: =SUM(W95:Z95) -> 130.09
B96: Total | C96: 0 | D96: 0 | E96: 0 | F96: 0 | G96: 0 | H96: 0 | I96: 0 | J96: 0 | K96: 0 | L96: 0 | M96: 0 | N96: 0 | O96: 0 | P96: 0 | Q96: 0 | R96: 0 | S96: 4.169 | T96: 1.866 | U96: 8.281 | V96: 41.69 | W96: 70.14 | X96: 14.732 | Y96: 27.267 | Z96: 17.951 | AA96: =SUM(W96:Z96) -> 130.09

Sheet IFRS - Credit operations
B2: Nu Holdings Ltd.
B3: Credit Operations
B4: Amounts in million of US$
B5: Back to Contents
C9: 30/06/2020 | D9: 31/12/2020 | E9: 31/03/2021 | F9: 30/06/2021 | G9: 30/09/2021 | H9: 31/12/2021 | I9: 31/03/2022 | J9: 30/06/2022 | K9: 30/09/2022 | L9: 31/12/2022 | M9: 31/03/2023 | N9: 30/06/2023 | O9: 30/09/2023 | P9: 31/12/2023 | Q9: 31/03/2024 | R9: 30/06/2024 | S9: 30/09/2024 | T9: 31/12/2024 | U9: 31/03/2025 | V9: 30/06/2025 | W9: 30/09/2025 | X9: 31/12/2025
B10: Credit card receivables | C10: US$ | D10: US$ | E10: US$ | F10: US$ | G10: US$ | H10: US$ | I10: US$ | J10: US$ | K10: US$ | L10: US$ | M10: US$ | N10: US$ | O10: US$ | P10: US$ | Q10: US$ | R10: US$ | S10: US$ | T10: US$ | U10: US$ | V10: US$ | W10: US$ | X10: US$
B11: Credit Card Receivables | C11: 2225.801 | D11: 3118.872 | E11: 2994.691 | F11: 4087.424 | G11: 4367.874 | H11: 5162.153 | I11: 6803.234 | J11: 7163.201 | K11: 7799.6 | L11: 9266.225 | M11: 10454.597 | N11: 12036.118 | O11: 12316.155 | P11: 14488.304 | Q11: 15093.727 | R11: 14315.159 | S11: 15186.768 | T11: 14619.312 | U11: 16269.154 | V11: 18224.677 | W11: 20028.127 | X11: 21751.226
B12: Total receivables | C12: 2225.801 | D12: 3118.872 | E12: 2994.691 | F12: 4087.424 | G12: 4367.874 | H12: 5162.153 | I12: 6803.234 | J12: 7163.201 | K12: 7799.6 | L12: 9266.225 | M12: 10454.597 | N12: 12036.118 | O12: 12316.155 | P12: 14488.304 | Q12: 15093.727 | R12: 14315.159 | S12: 15186.768 | T12: 14619.312 | U12: 16269.154 | V12: 18224.677 | W12: 20028.127 | X12: 21751.226
B13: Fair value adjustment - portfolio hedge | I13: -0.07 | J13: -0.212 | K13: -0.061 | L13: -0.051 | M13: -0.018 | N13: 0.01 | O13: 0.023 | P13: 0.032
B14: Total | C14: 2225.801 | D14: 3118.872 | E14: 2994.691 | F14: 4087.424 | G14: 4367.874 | H14: 5162.153 | I14: 6803.164 | J14: 7162.989 | K14: 7799.539 | L14: 9266.174 | M14: 10454.579 | N14: 12036.128 | O14: 12316.178 | P14: 14488.336 | Q14: 15093.727 | R14: 14315.159 | S14: 15186.768 | T14: 14619.312 | U14: 16269.154 | V14: 18224.677 | W14: 20028.127 | X14: 21751.226
B16: Credit card expected credit loss
B17: Presented as deduction of receivables | C17: -182.189 | D17: -209.965 | E17: -206.878 | F17: -267.533 | G17: -306.369 | H17: -381.633 | I17: -568.34 | J17: -684.519 | K17: -811.591 | L17: -1033.102 | M17: -1296.127 | N17: -1648.415 | O17: -1820.654 | P17: -2074.203 | Q17: -2297.05 | R17: -2287.823 | S17: -2497.558 | T17: -2360.036 | U17: -2728.416 | V17: -3095.148 | W17: -3255.677 | X17: -3483.322
B18: Presented as "Other liabilities" | D18: -7.577 | E18: -8.564 | F18: -7.494 | G18: -7.954 | H18: -9.046 | I18: -12.15 | J18: -12.828 | K18: -12.734 | L18: -17.566 | M18: -19.901 | N18: -25.856 | O18: -30.408 | P18: -22.066 | Q18: -22.443 | R18: -25.22 | S18: -28.836 | T18: -29.49 | U18: -34.908 | V18: -38.673 | W18: -49.072 | X18: -44.679
B19: Total credit card expected credit loss | C19: -182.189 | D19: -217.542 | E19: -215.442 | F19: -275.027 | G19: -314.323 | H19: -390.679 | I19: -580.49 | J19: -697.347 | K19: -824.325 | L19: -1050.668 | M19: -1316.028 | N19: -1674.271 | O19: -1851.062 | P19: -2096.269 | Q19: -2319.493 | R19: -2313.043 | S19: -2526.394 | T19: -2389.526 | U19: -2763.324 | V19: -3133.821 | W19: -3304.749 | X19: -3528.001
B20: Receivables, net | C20: 2043.612 | D20: 2901.33 | E20: 2779.249 | F20: 3812.397 | G20: 4053.551 | H20: 4771.474 | I20: 6222.674 | J20: 6465.642 | K20: 6975.214 | L20: 8215.506 | M20: 9138.551 | N20: 10361.857 | O20: 10465.116 | P20: 12392.067 | Q20: 12774.234 | R20: 12002.116 | S20: 12660.374 | T20: 12229.786 | U20: 13505.83 | V20: 15090.856 | W20: 16723.378 | X20: 18223.225
B21: Total receivables presented as assets | C21: 2043.612 | D21: 2908.907 | E21: 2787.813 | F21: 3819.891 | G21: 4061.505 | H21: 4780.52 | I21: 6234.824 | J21: 6478.47 | K21: 6987.948 | L21: 8233.072 | M21: 9158.452 | N21: 10387.713 | O21: 10495.524 | P21: 12414.133 | Q21: 12796.677 | R21: 12027.336 | S21: 12689.21 | T21: 12259.276 | U21: 13540.738 | V21: 15129.529 | W21: 16772.45 | X21: 18267.904
B23: Lending receivables
B24: Loans to individuals | C24: 60.848 | D24: 200.904 | E24: 303.897 | F24: 592.454 | G24: 903.061 | H24: 1392.35 | I24: 2009.494 | J24: 1952.511 | K24: 1907.405 | L24: 1976.499 | M24: 2337.419 | N24: 2791.818 | O24: 3090.736 | P24: 3691.436 | Q24: 4478.706 | R24: 4631.65 | S24: 5691.987 | T24: 5864.27 | U24: 7496.996 | V24: 8576.887 | W24: 9724.037 | X24: 10149.892
B25: Loans to companies | P25: 22.334 | T25: 252.185 | U25: 351.064 | V25: 478.958 | W25: 637.935 | X25: 765.561
B26: Total loans | C26: 60.848 | D26: 200.904 | E26: 303.897 | F26: 592.454 | G26: 903.061 | H26: 1392.35 | I26: 2009.494 | J26: 1952.511 | K26: 1907.405 | L26: 1976.499 | M26: 2337.419 | N26: 2791.818 | O26: 3090.736 | P26: 3713.77 | Q26: 4478.706 | R26: 4631.65 | S26: 5691.987 | T26: 6116.455 | U26: 7848.06 | V26: 9055.845 | W26: 10361.972 | X26: 10915.453
B27: Loan expected credit loss | C27: -11.672 | D27: -26.21 | E27: -39.355 | F27: -72.768 | G27: -110.325 | H27: -197.536 | I27: -340.517 | J27: -270.277 | K27: -301.63 | L27: -300.223 | M27: -315.911 | N27: -358.601 | O27: -401.328 | P27: -512.134 | Q27: -614.894 | R27: -623.449 | S27: -752.611 | T27: -794.57 | U27: -1035.404 | V27: -1185.593 | W27: -1380.214 | X27: -1493.995
B28: Total receivables | C28: 49.176 | D28: 174.694 | E28: 264.542 | F28: 519.686 | G28: 792.736 | H28: 1194.814 | I28: 1668.977 | J28: 1682.234 | K28: 1605.775 | L28: 1676.276 | M28: 2021.508 | N28: 2433.217 | O28: 2689.408 | P28: 3201.636 | Q28: 3863.812 | R28: 4008.201 | S28: 4939.376 | T28: 5321.885 | U28: 6812.656 | V28: 7870.252 | W28: 8981.758 | X28: 9421.458
B29: Fair value adjustment - portfolio hedge | I29: -1.46 | J29: -6.458 | K29: -2.67 | L29: -2.836 | M29: -1.317 | N29: -0.008 | O29: 0.57 | P29: 0.698
B30: Total | C30: 49.176 | D30: 174.694 | E30: 264.542 | F30: 519.686 | G30: 792.736 | H30: 1194.814 | I30: 1667.517 | J30: 1675.776 | K30: 1603.105 | L30: 1673.44 | M30: 2020.191 | N30: 2433.209 | O30: 2689.978 | P30: 3202.334 | Q30: 3863.812 | R30: 4008.201 | S30: 4939.376 | T30: 5321.885 | U30: 6812.656 | V30: 7870.252 | W30: 8981.758 | X30: 9421.458
B32: Other receivables
B33: Other receivables | H33: 50.349 | I33: 285.632 | J33: 374.188 | K33: 381.782 | L33: 522.734 | M33: 1078.801 | N33: 1349.226 | O33: 1603.234 | P33: 1691.665 | Q33: 1408.209 | R33: 955.613 | S33: 973.023 | T33: 1415.263 | U33: 889.59 | V33: 931.343 | W33: 989.766 | X33: 1002.629
B34: Other receivables - ECL | L34: -1.064 | M34: -2.12 | N34: -2.666 | O34: -2.499 | P34: -2.635 | Q34: -2.24 | R34: -1.566 | S34: -1.737 | T34: -1.82 | U34: -1.96 | V34: -1.81 | W34: -1.922 | X34: -1.946
B35: Total | H35: 50.349 | I35: 285.632 | J35: 374.188 | K35: 381.782 | L35: 521.67 | M35: 1076.681 | N35: 1346.56 | O35: 1600.735 | P35: 1689.03 | Q35: 1405.969 | R35: 954.047 | S35: 971.286 | T35: 1413.443 | U35: 887.63 | V35: 929.533 | W35: 987.844 | X35: 1000.683
C41: 30/06/2020 | D41: 31/12/2020 | E41: 31/03/2021 | F41: 30/06/2021 | G41: 30/09/2021 | H41: 31/12/2021 | I41: 31/03/2022 | J41: 30/06/2022 | K41: 30/09/2022 | L41: 31/12/2022 | M41: 31/03/2023 | N41: 30/06/2023 | O41: 30/09/2023 | P41: 31/12/2023 | Q41: 31/03/2024 | R41: 30/06/2024 | S41: 30/09/2024 | T41: 31/12/2024 | U41: 31/03/2025 | V41: 30/06/2025 | W41: 30/09/2025 | X41: 31/12/2025
B43: Credit card portfolio | C43: -58.099 | D43: -116.856 | E43: -43.248 | F43: -71.767 | G43: -94.346 | H43: -94.346 | I43: -50.608 | J43: -100.089 | K43: -182.333 | L43: -290.974 | M43: -174.938 | N43: -385.835 | O43: -627.447 | P43: -935.283 | Q43: -315.394 | R43: -618.81 | S43: -973.563 | T43: -1374.04 | U43: -451.78 | V43: -907.422 | W43: -1349.842 | X43: -1852.246
B44: Lending portfolio | C44: -0.293 | D44: -4.525 | E44: -3.614 | F44: -7.03 | G44: -9.276 | H44: -13.223 | I44: -11.696 | J44: -169.452 | K44: -282.374 | L44: -408.605 | M44: -106.614 | N44: -214.477 | O44: -330.144 | P44: -451.387 | Q44: -169.733 | R44: -380.973 | S44: -596.87 | T44: -814.913 | U44: -259.478 | V44: -606.999 | W44: -983.267 | X44: -1399.958
B45: Total write-offs | C45: -58.392 | D45: -121.381 | E45: -46.862 | F45: -78.797 | G45: -103.622 | H45: -107.569 | I45: -62.304 | J45: -269.541 | K45: -464.707 | L45: -699.579 | M45: -281.552 | N45: -600.312 | O45: -957.591 | P45: -1386.67 | Q45: -485.127 | R45: -999.783 | S45: -1570.433 | T45: -2188.953 | U45: -711.258 | V45: -1514.421 | W45: -2333.109 | X45: -3252.204
B47: Credit card portfolio | C47: 6.558 | D47: 18.202 | E47: 5.868 | F47: 5.811 | G47: 18.079 | H47: 22.494 | I47: 3.545 | J47: 9.754 | K47: 18.27 | L47: 31.491 | M47: 13.386 | N47: 32.077 | O47: 71.125 | P47: 158.747 | Q47: 39.611 | R47: 87.937 | S47: 132.292 | T47: 192.415 | U47: 63.205 | V47: 127.29 | W47: 215.153 | X47: 312.947
B48: Lending portfolio | C48: 0.058 | D48: 0.103 | E48: 0.048 | F48: 0.126 | G48: 0.358 | H48: 0.542 | I48: 0.222 | J48: 1.217 | K48: 1.869 | L48: 4.52 | M48: 3.756 | N48: 9.494 | O48: 20.994 | P48: 43.683 | Q48: 13.168 | R48: 40.069 | S48: 72.747 | T48: 107.646 | U48: 37.822 | V48: 76.728 | W48: 126.237 | X48: 183.235
B49: Total Recoveries | C49: 6.616 | D49: 18.305 | E49: 5.916 | F49: 5.937 | G49: 18.437 | H49: 23.036 | I49: 3.767 | J49: 10.971 | K49: 20.139 | L49: 36.011 | M49: 17.142 | N49: 41.571 | O49: 92.119 | P49: 202.43 | Q49: 52.779 | R49: 128.006 | S49: 205.039 | T49: 300.061 | U49: 101.027 | V49: 204.018 | W49: 341.39 | X49: 496.182
B50: The information included in this table is acumulated as of date.
